{"info":{"file":"common/network/requests/SetEmpowerRequest.js","fileShort":"common/network/requests/SetEmpowerRequest.js","fileSafe":"common_network_requests_SetEmpowerRequest_js","link":"files/common_network_requests_SetEmpowerRequest_js/index.html"},"complexity":{"methodAggregate":{"cyclomatic":1,"cyclomaticDensity":25,"halstead":{"bugs":0.045,"difficulty":5.833,"effort":780.401,"length":30,"time":43.356,"vocabulary":22,"volume":133.783,"operands":{"distinct":12,"total":14,"identifiers":["__stripped__"]},"operators":{"distinct":10,"total":16,"identifiers":["__stripped__"]}},"params":0,"sloc":{"logical":4,"physical":23}},"settings":{"commonjs":false,"forin":false,"logicalor":true,"switchcase":true,"trycatch":false,"newmi":true},"classes":[{"methodAggregate":{"cyclomatic":1,"cyclomaticDensity":33.333,"halstead":{"bugs":0.025,"difficulty":2.5,"effort":185.577,"length":19,"time":10.31,"vocabulary":15,"volume":74.231,"operands":{"distinct":10,"total":10,"identifiers":["__stripped__"]},"operators":{"distinct":5,"total":9,"identifiers":["__stripped__"]}},"params":0,"sloc":{"logical":3,"physical":15}},"errors":[],"lineEnd":22,"lineStart":8,"methods":[{"cyclomatic":1,"cyclomaticDensity":100,"halstead":{"bugs":0.001,"difficulty":0.5,"effort":1,"length":2,"time":0.056,"vocabulary":2,"volume":2,"operands":{"distinct":1,"total":1,"identifiers":["__stripped__"]},"operators":{"distinct":1,"total":1,"identifiers":["__stripped__"]}},"params":0,"sloc":{"logical":1,"physical":3},"errors":[],"lineEnd":12,"lineStart":10,"name":"getRequestName","complexity":{"cyclomatic":1,"sloc":{"logical":1,"physical":3},"halstead":{"bugs":0.001,"difficulty":0.5,"effort":1,"length":2,"time":0.056,"vocabulary":2,"volume":2,"operands":{"distinct":1,"total":1,"identifiers":["__stripped__"]},"operators":{"distinct":1,"total":1,"identifiers":["__stripped__"]}}},"line":10},{"cyclomatic":1,"cyclomaticDensity":100,"halstead":{"bugs":0.005,"difficulty":1.5,"effort":23.265,"length":6,"time":1.292,"vocabulary":6,"volume":15.51,"operands":{"distinct":3,"total":3,"identifiers":["__stripped__"]},"operators":{"distinct":3,"total":3,"identifiers":["__stripped__"]}},"params":0,"sloc":{"logical":1,"physical":3},"errors":[],"lineEnd":16,"lineStart":14,"name":"getRelativeUrl","complexity":{"cyclomatic":1,"sloc":{"logical":1,"physical":3},"halstead":{"bugs":0.005,"difficulty":1.5,"effort":23.265,"length":6,"time":1.292,"vocabulary":6,"volume":15.51,"operands":{"distinct":3,"total":3,"identifiers":["__stripped__"]},"operators":{"distinct":3,"total":3,"identifiers":["__stripped__"]}}},"line":14},{"cyclomatic":1,"cyclomaticDensity":100,"halstead":{"bugs":0.002,"difficulty":1,"effort":4.755,"length":3,"time":0.264,"vocabulary":3,"volume":4.755,"operands":{"distinct":1,"total":1,"identifiers":["__stripped__"]},"operators":{"distinct":2,"total":2,"identifiers":["__stripped__"]}},"params":0,"sloc":{"logical":1,"physical":3},"errors":[],"lineEnd":20,"lineStart":18,"name":"getSign","complexity":{"cyclomatic":1,"sloc":{"logical":1,"physical":3},"halstead":{"bugs":0.002,"difficulty":1,"effort":4.755,"length":3,"time":0.264,"vocabulary":3,"volume":4.755,"operands":{"distinct":1,"total":1,"identifiers":["__stripped__"]},"operators":{"distinct":2,"total":2,"identifiers":["__stripped__"]}}},"line":18}],"methodAverage":{"cyclomatic":1,"cyclomaticDensity":100,"halstead":{"bugs":0.002,"difficulty":1,"effort":9.673,"length":3.667,"time":0.537,"vocabulary":3.667,"volume":7.422,"operands":{"distinct":1.667,"total":1.667},"operators":{"distinct":2,"total":2}},"params":0,"sloc":{"logical":1,"physical":3}},"name":"SetEmpowerRequest","maintainability":95.461}],"dependencies":[{"line":2,"path":"../BaseRequest.js","type":"esm"},{"line":3,"path":"../ServiceAddress.js","type":"esm"}],"errors":[],"lineEnd":23,"lineStart":1,"maintainability":95.461,"methods":[],"methodAverage":{"cyclomatic":1,"cyclomaticDensity":100,"halstead":{"bugs":0.002,"difficulty":1,"effort":9.673,"length":3.667,"time":0.537,"vocabulary":3.667,"volume":7.422,"operands":{"distinct":1.667,"total":1.667},"operators":{"distinct":2,"total":2}},"params":0,"sloc":{"logical":1,"physical":3}},"module":"common/network/requests/SetEmpowerRequest.js","aggregate":{"complexity":{"cyclomatic":1,"cyclomaticDensity":25,"halstead":{"bugs":0.045,"difficulty":5.833,"effort":780.401,"length":30,"time":43.356,"vocabulary":22,"volume":133.783,"operands":{"distinct":12,"total":14,"identifiers":["__stripped__"]},"operators":{"distinct":10,"total":16,"identifiers":["__stripped__"]}},"params":0,"sloc":{"logical":4,"physical":23}}},"functions":[{"cyclomatic":1,"cyclomaticDensity":100,"halstead":{"bugs":0.001,"difficulty":0.5,"effort":1,"length":2,"time":0.056,"vocabulary":2,"volume":2,"operands":{"distinct":1,"total":1,"identifiers":["__stripped__"]},"operators":{"distinct":1,"total":1,"identifiers":["__stripped__"]}},"params":0,"sloc":{"logical":1,"physical":3},"errors":[],"lineEnd":12,"lineStart":10,"name":"getRequestName","complexity":{"cyclomatic":1,"sloc":{"logical":1,"physical":3},"halstead":{"bugs":0.001,"difficulty":0.5,"effort":1,"length":2,"time":0.056,"vocabulary":2,"volume":2,"operands":{"distinct":1,"total":1,"identifiers":["__stripped__"]},"operators":{"distinct":1,"total":1,"identifiers":["__stripped__"]}}},"line":10},{"cyclomatic":1,"cyclomaticDensity":100,"halstead":{"bugs":0.005,"difficulty":1.5,"effort":23.265,"length":6,"time":1.292,"vocabulary":6,"volume":15.51,"operands":{"distinct":3,"total":3,"identifiers":["__stripped__"]},"operators":{"distinct":3,"total":3,"identifiers":["__stripped__"]}},"params":0,"sloc":{"logical":1,"physical":3},"errors":[],"lineEnd":16,"lineStart":14,"name":"getRelativeUrl","complexity":{"cyclomatic":1,"sloc":{"logical":1,"physical":3},"halstead":{"bugs":0.005,"difficulty":1.5,"effort":23.265,"length":6,"time":1.292,"vocabulary":6,"volume":15.51,"operands":{"distinct":3,"total":3,"identifiers":["__stripped__"]},"operators":{"distinct":3,"total":3,"identifiers":["__stripped__"]}}},"line":14},{"cyclomatic":1,"cyclomaticDensity":100,"halstead":{"bugs":0.002,"difficulty":1,"effort":4.755,"length":3,"time":0.264,"vocabulary":3,"volume":4.755,"operands":{"distinct":1,"total":1,"identifiers":["__stripped__"]},"operators":{"distinct":2,"total":2,"identifiers":["__stripped__"]}},"params":0,"sloc":{"logical":1,"physical":3},"errors":[],"lineEnd":20,"lineStart":18,"name":"getSign","complexity":{"cyclomatic":1,"sloc":{"logical":1,"physical":3},"halstead":{"bugs":0.002,"difficulty":1,"effort":4.755,"length":3,"time":0.264,"vocabulary":3,"volume":4.755,"operands":{"distinct":1,"total":1,"identifiers":["__stripped__"]},"operators":{"distinct":2,"total":2,"identifiers":["__stripped__"]}}},"line":18}]},"eslint":{"messages":[{"severity":"error","line":15,"column":41,"message":"Strings must use singlequote.","fix":{"range":[325,369],"text":"'ws/boss/order/car/security/doAuthorization'"}},{"severity":"error","line":19,"column":13,"message":"Strings must use singlequote.","fix":{"range":[405,414],"text":"'channel'"}}]}}