{"info":{"file":"common/lib/md5.js","fileShort":"common/lib/md5.js","fileSafe":"common_lib_md5_js","link":"files/common_lib_md5_js/index.html"},"complexity":{"methodAggregate":{"cyclomatic":11,"cyclomaticDensity":6.748,"halstead":{"bugs":4.21,"difficulty":100.926,"effort":1274589.74,"length":1665,"time":70810.541,"vocabulary":192,"volume":12628.963,"operands":{"distinct":162,"total":1090,"identifiers":["__stripped__"]},"operators":{"distinct":30,"total":575,"identifiers":["__stripped__"]}},"params":56,"sloc":{"logical":163,"physical":283}},"settings":{"commonjs":false,"forin":false,"logicalor":true,"switchcase":true,"trycatch":false,"newmi":true},"classes":[],"dependencies":[],"errors":[],"lineEnd":283,"lineStart":1,"maintainability":60.529,"methods":[{"cyclomatic":1,"cyclomaticDensity":33.333,"halstead":{"bugs":0.043,"difficulty":12,"effort":1553.401,"length":34,"time":86.3,"vocabulary":14,"volume":129.45,"operands":{"distinct":6,"total":18,"identifiers":["__stripped__"]},"operators":{"distinct":8,"total":16,"identifiers":["__stripped__"]}},"params":2,"sloc":{"logical":3,"physical":5},"errors":[],"lineEnd":33,"lineStart":29,"name":"safeAdd","complexity":{"cyclomatic":1,"sloc":{"logical":3,"physical":5},"halstead":{"bugs":0.043,"difficulty":12,"effort":1553.401,"length":34,"time":86.3,"vocabulary":14,"volume":129.45,"operands":{"distinct":6,"total":18,"identifiers":["__stripped__"]},"operators":{"distinct":8,"total":16,"identifiers":["__stripped__"]}}},"line":29},{"cyclomatic":1,"cyclomaticDensity":100,"halstead":{"bugs":0.012,"difficulty":5.833,"effort":210,"length":12,"time":11.667,"vocabulary":8,"volume":36,"operands":{"distinct":3,"total":7,"identifiers":["__stripped__"]},"operators":{"distinct":5,"total":5,"identifiers":["__stripped__"]}},"params":2,"sloc":{"logical":1,"physical":3},"errors":[],"lineEnd":40,"lineStart":38,"name":"bitRotateLeft","complexity":{"cyclomatic":1,"sloc":{"logical":1,"physical":3},"halstead":{"bugs":0.012,"difficulty":5.833,"effort":210,"length":12,"time":11.667,"vocabulary":8,"volume":36,"operands":{"distinct":3,"total":7,"identifiers":["__stripped__"]},"operators":{"distinct":5,"total":5,"identifiers":["__stripped__"]}}},"line":38},{"cyclomatic":1,"cyclomaticDensity":100,"halstead":{"bugs":0.025,"difficulty":2.125,"effort":162.359,"length":23,"time":9.02,"vocabulary":10,"volume":76.404,"operands":{"distinct":8,"total":17,"identifiers":["__stripped__"]},"operators":{"distinct":2,"total":6,"identifiers":["__stripped__"]}},"params":6,"sloc":{"logical":1,"physical":3},"errors":[],"lineEnd":47,"lineStart":45,"name":"md5cmn","complexity":{"cyclomatic":1,"sloc":{"logical":1,"physical":3},"halstead":{"bugs":0.025,"difficulty":2.125,"effort":162.359,"length":23,"time":9.02,"vocabulary":10,"volume":76.404,"operands":{"distinct":8,"total":17,"identifiers":["__stripped__"]},"operators":{"distinct":2,"total":6,"identifiers":["__stripped__"]}}},"line":45},{"cyclomatic":1,"cyclomaticDensity":100,"halstead":{"bugs":0.028,"difficulty":5.313,"effort":452.147,"length":23,"time":25.119,"vocabulary":13,"volume":85.11,"operands":{"distinct":8,"total":17,"identifiers":["__stripped__"]},"operators":{"distinct":5,"total":6,"identifiers":["__stripped__"]}},"params":7,"sloc":{"logical":1,"physical":3},"errors":[],"lineEnd":50,"lineStart":48,"name":"md5ff","complexity":{"cyclomatic":1,"sloc":{"logical":1,"physical":3},"halstead":{"bugs":0.028,"difficulty":5.313,"effort":452.147,"length":23,"time":25.119,"vocabulary":13,"volume":85.11,"operands":{"distinct":8,"total":17,"identifiers":["__stripped__"]},"operators":{"distinct":5,"total":6,"identifiers":["__stripped__"]}}},"line":48},{"cyclomatic":1,"cyclomaticDensity":100,"halstead":{"bugs":0.028,"difficulty":5.313,"effort":452.147,"length":23,"time":25.119,"vocabulary":13,"volume":85.11,"operands":{"distinct":8,"total":17,"identifiers":["__stripped__"]},"operators":{"distinct":5,"total":6,"identifiers":["__stripped__"]}},"params":7,"sloc":{"logical":1,"physical":3},"errors":[],"lineEnd":53,"lineStart":51,"name":"md5gg","complexity":{"cyclomatic":1,"sloc":{"logical":1,"physical":3},"halstead":{"bugs":0.028,"difficulty":5.313,"effort":452.147,"length":23,"time":25.119,"vocabulary":13,"volume":85.11,"operands":{"distinct":8,"total":17,"identifiers":["__stripped__"]},"operators":{"distinct":5,"total":6,"identifiers":["__stripped__"]}}},"line":51},{"cyclomatic":1,"cyclomaticDensity":100,"halstead":{"bugs":0.023,"difficulty":3,"effort":207.566,"length":20,"time":11.531,"vocabulary":11,"volume":69.189,"operands":{"distinct":8,"total":16,"identifiers":["__stripped__"]},"operators":{"distinct":3,"total":4,"identifiers":["__stripped__"]}},"params":7,"sloc":{"logical":1,"physical":3},"errors":[],"lineEnd":56,"lineStart":54,"name":"md5hh","complexity":{"cyclomatic":1,"sloc":{"logical":1,"physical":3},"halstead":{"bugs":0.023,"difficulty":3,"effort":207.566,"length":20,"time":11.531,"vocabulary":11,"volume":69.189,"operands":{"distinct":8,"total":16,"identifiers":["__stripped__"]},"operators":{"distinct":3,"total":4,"identifiers":["__stripped__"]}}},"line":54},{"cyclomatic":1,"cyclomaticDensity":100,"halstead":{"bugs":0.026,"difficulty":5,"effort":388.546,"length":21,"time":21.586,"vocabulary":13,"volume":77.709,"operands":{"distinct":8,"total":16,"identifiers":["__stripped__"]},"operators":{"distinct":5,"total":5,"identifiers":["__stripped__"]}},"params":7,"sloc":{"logical":1,"physical":3},"errors":[],"lineEnd":59,"lineStart":57,"name":"md5ii","complexity":{"cyclomatic":1,"sloc":{"logical":1,"physical":3},"halstead":{"bugs":0.026,"difficulty":5,"effort":388.546,"length":21,"time":21.586,"vocabulary":13,"volume":77.709,"operands":{"distinct":8,"total":16,"identifiers":["__stripped__"]},"operators":{"distinct":5,"total":5,"identifiers":["__stripped__"]}}},"line":57},{"cyclomatic":2,"cyclomaticDensity":2.353,"halstead":{"bugs":2.579,"difficulty":58.959,"effort":456135.471,"length":1107,"time":25340.859,"vocabulary":127,"volume":7736.474,"operands":{"distinct":110,"total":763,"identifiers":["__stripped__"]},"operators":{"distinct":17,"total":344,"identifiers":["__stripped__"]}},"params":2,"sloc":{"logical":85,"physical":96},"errors":[],"lineEnd":159,"lineStart":64,"name":"binlMD5","complexity":{"cyclomatic":2,"sloc":{"logical":85,"physical":96},"halstead":{"bugs":2.579,"difficulty":58.959,"effort":456135.471,"length":1107,"time":25340.859,"vocabulary":127,"volume":7736.474,"operands":{"distinct":110,"total":763,"identifiers":["__stripped__"]},"operators":{"distinct":17,"total":344,"identifiers":["__stripped__"]}}},"line":64},{"cyclomatic":2,"cyclomaticDensity":33.333,"halstead":{"bugs":0.07,"difficulty":12.923,"effort":2703.702,"length":44,"time":150.206,"vocabulary":27,"volume":209.215,"operands":{"distinct":13,"total":24,"identifiers":["__stripped__"]},"operators":{"distinct":14,"total":20,"identifiers":["__stripped__"]}},"params":1,"sloc":{"logical":6,"physical":9},"errors":[],"lineEnd":172,"lineStart":164,"name":"binl2rstr","complexity":{"cyclomatic":2,"sloc":{"logical":6,"physical":9},"halstead":{"bugs":0.07,"difficulty":12.923,"effort":2703.702,"length":44,"time":150.206,"vocabulary":27,"volume":209.215,"operands":{"distinct":13,"total":24,"identifiers":["__stripped__"]},"operators":{"distinct":14,"total":20,"identifiers":["__stripped__"]}}},"line":164},{"cyclomatic":3,"cyclomaticDensity":33.333,"halstead":{"bugs":0.122,"difficulty":24.286,"effort":8903.399,"length":74,"time":494.633,"vocabulary":31,"volume":366.611,"operands":{"distinct":14,"total":40,"identifiers":["__stripped__"]},"operators":{"distinct":17,"total":34,"identifiers":["__stripped__"]}},"params":1,"sloc":{"logical":9,"physical":13},"errors":[],"lineEnd":190,"lineStart":178,"name":"rstr2binl","complexity":{"cyclomatic":3,"sloc":{"logical":9,"physical":13},"halstead":{"bugs":0.122,"difficulty":24.286,"effort":8903.399,"length":74,"time":494.633,"vocabulary":31,"volume":366.611,"operands":{"distinct":14,"total":40,"identifiers":["__stripped__"]},"operators":{"distinct":17,"total":34,"identifiers":["__stripped__"]}}},"line":178},{"cyclomatic":1,"cyclomaticDensity":100,"halstead":{"bugs":0.016,"difficulty":2.667,"effort":124.019,"length":14,"time":6.89,"vocabulary":10,"volume":46.507,"operands":{"distinct":6,"total":8,"identifiers":["__stripped__"]},"operators":{"distinct":4,"total":6,"identifiers":["__stripped__"]}},"params":1,"sloc":{"logical":1,"physical":3},"errors":[],"lineEnd":197,"lineStart":195,"name":"rstrMD5","complexity":{"cyclomatic":1,"sloc":{"logical":1,"physical":3},"halstead":{"bugs":0.016,"difficulty":2.667,"effort":124.019,"length":14,"time":6.89,"vocabulary":10,"volume":46.507,"operands":{"distinct":6,"total":8,"identifiers":["__stripped__"]},"operators":{"distinct":4,"total":6,"identifiers":["__stripped__"]}}},"line":195},{"cyclomatic":3,"cyclomaticDensity":23.077,"halstead":{"bugs":0.179,"difficulty":17.818,"effort":9580.341,"length":104,"time":532.241,"vocabulary":36,"volume":537.672,"operands":{"distinct":22,"total":56,"identifiers":["__stripped__"]},"operators":{"distinct":14,"total":48,"identifiers":["__stripped__"]}},"params":2,"sloc":{"logical":13,"physical":17},"errors":[],"lineEnd":218,"lineStart":202,"name":"rstrHMACMD5","complexity":{"cyclomatic":3,"sloc":{"logical":13,"physical":17},"halstead":{"bugs":0.179,"difficulty":17.818,"effort":9580.341,"length":104,"time":532.241,"vocabulary":36,"volume":537.672,"operands":{"distinct":22,"total":56,"identifiers":["__stripped__"]},"operators":{"distinct":14,"total":48,"identifiers":["__stripped__"]}}},"line":202},{"cyclomatic":2,"cyclomaticDensity":25,"halstead":{"bugs":0.082,"difficulty":11.393,"effort":2804.06,"length":53,"time":155.781,"vocabulary":25,"volume":246.124,"operands":{"distinct":14,"total":29,"identifiers":["__stripped__"]},"operators":{"distinct":11,"total":24,"identifiers":["__stripped__"]}},"params":1,"sloc":{"logical":8,"physical":11},"errors":[],"lineEnd":233,"lineStart":223,"name":"rstr2hex","complexity":{"cyclomatic":2,"sloc":{"logical":8,"physical":11},"halstead":{"bugs":0.082,"difficulty":11.393,"effort":2804.06,"length":53,"time":155.781,"vocabulary":25,"volume":246.124,"operands":{"distinct":14,"total":29,"identifiers":["__stripped__"]},"operators":{"distinct":11,"total":24,"identifiers":["__stripped__"]}}},"line":223},{"cyclomatic":1,"cyclomaticDensity":100,"halstead":{"bugs":0.005,"difficulty":1.333,"effort":21.671,"length":7,"time":1.204,"vocabulary":5,"volume":16.253,"operands":{"distinct":3,"total":4,"identifiers":["__stripped__"]},"operators":{"distinct":2,"total":3,"identifiers":["__stripped__"]}},"params":1,"sloc":{"logical":1,"physical":3},"errors":[],"lineEnd":240,"lineStart":238,"name":"str2rstrUTF8","complexity":{"cyclomatic":1,"sloc":{"logical":1,"physical":3},"halstead":{"bugs":0.005,"difficulty":1.333,"effort":21.671,"length":7,"time":1.204,"vocabulary":5,"volume":16.253,"operands":{"distinct":3,"total":4,"identifiers":["__stripped__"]},"operators":{"distinct":2,"total":3,"identifiers":["__stripped__"]}}},"line":238},{"cyclomatic":1,"cyclomaticDensity":100,"halstead":{"bugs":0.005,"difficulty":1.333,"effort":21.671,"length":7,"time":1.204,"vocabulary":5,"volume":16.253,"operands":{"distinct":3,"total":4,"identifiers":["__stripped__"]},"operators":{"distinct":2,"total":3,"identifiers":["__stripped__"]}},"params":1,"sloc":{"logical":1,"physical":3},"errors":[],"lineEnd":247,"lineStart":245,"name":"rawMD5","complexity":{"cyclomatic":1,"sloc":{"logical":1,"physical":3},"halstead":{"bugs":0.005,"difficulty":1.333,"effort":21.671,"length":7,"time":1.204,"vocabulary":5,"volume":16.253,"operands":{"distinct":3,"total":4,"identifiers":["__stripped__"]},"operators":{"distinct":2,"total":3,"identifiers":["__stripped__"]}}},"line":245},{"cyclomatic":1,"cyclomaticDensity":100,"halstead":{"bugs":0.005,"difficulty":1.333,"effort":21.671,"length":7,"time":1.204,"vocabulary":5,"volume":16.253,"operands":{"distinct":3,"total":4,"identifiers":["__stripped__"]},"operators":{"distinct":2,"total":3,"identifiers":["__stripped__"]}},"params":1,"sloc":{"logical":1,"physical":3},"errors":[],"lineEnd":250,"lineStart":248,"name":"hexMD5","complexity":{"cyclomatic":1,"sloc":{"logical":1,"physical":3},"halstead":{"bugs":0.005,"difficulty":1.333,"effort":21.671,"length":7,"time":1.204,"vocabulary":5,"volume":16.253,"operands":{"distinct":3,"total":4,"identifiers":["__stripped__"]},"operators":{"distinct":2,"total":3,"identifiers":["__stripped__"]}}},"line":248},{"cyclomatic":1,"cyclomaticDensity":100,"halstead":{"bugs":0.009,"difficulty":1.75,"effort":49.761,"length":11,"time":2.764,"vocabulary":6,"volume":28.435,"operands":{"distinct":4,"total":7,"identifiers":["__stripped__"]},"operators":{"distinct":2,"total":4,"identifiers":["__stripped__"]}},"params":2,"sloc":{"logical":1,"physical":3},"errors":[],"lineEnd":253,"lineStart":251,"name":"rawHMACMD5","complexity":{"cyclomatic":1,"sloc":{"logical":1,"physical":3},"halstead":{"bugs":0.009,"difficulty":1.75,"effort":49.761,"length":11,"time":2.764,"vocabulary":6,"volume":28.435,"operands":{"distinct":4,"total":7,"identifiers":["__stripped__"]},"operators":{"distinct":2,"total":4,"identifiers":["__stripped__"]}}},"line":251},{"cyclomatic":1,"cyclomaticDensity":100,"halstead":{"bugs":0.008,"difficulty":1.5,"effort":34.897,"length":9,"time":1.939,"vocabulary":6,"volume":23.265,"operands":{"distinct":4,"total":6,"identifiers":["__stripped__"]},"operators":{"distinct":2,"total":3,"identifiers":["__stripped__"]}},"params":2,"sloc":{"logical":1,"physical":3},"errors":[],"lineEnd":256,"lineStart":254,"name":"hexHMACMD5","complexity":{"cyclomatic":1,"sloc":{"logical":1,"physical":3},"halstead":{"bugs":0.008,"difficulty":1.5,"effort":34.897,"length":9,"time":1.939,"vocabulary":6,"volume":23.265,"operands":{"distinct":4,"total":6,"identifiers":["__stripped__"]},"operators":{"distinct":2,"total":3,"identifiers":["__stripped__"]}}},"line":254},{"cyclomatic":4,"cyclomaticDensity":57.143,"halstead":{"bugs":0.035,"difficulty":4.571,"effort":474.436,"length":30,"time":26.358,"vocabulary":11,"volume":103.783,"operands":{"distinct":7,"total":16,"identifiers":["__stripped__"]},"operators":{"distinct":4,"total":14,"identifiers":["__stripped__"]}},"params":3,"sloc":{"logical":7,"physical":12},"errors":[],"lineEnd":269,"lineStart":258,"name":"md5","complexity":{"cyclomatic":4,"sloc":{"logical":7,"physical":12},"halstead":{"bugs":0.035,"difficulty":4.571,"effort":474.436,"length":30,"time":26.358,"vocabulary":11,"volume":103.783,"operands":{"distinct":7,"total":16,"identifiers":["__stripped__"]},"operators":{"distinct":4,"total":14,"identifiers":["__stripped__"]}}},"line":258}],"methodAverage":{"cyclomatic":1.526,"cyclomaticDensity":74.083,"halstead":{"bugs":0.174,"difficulty":9.392,"effort":25489.54,"length":85.421,"time":1416.086,"vocabulary":19.789,"volume":521.359,"operands":{"distinct":13.263,"total":56.263},"operators":{"distinct":6.526,"total":29.158}},"params":2.947,"sloc":{"logical":7.526,"physical":10.474}},"module":"common/lib/md5.js","aggregate":{"complexity":{"cyclomatic":11,"cyclomaticDensity":6.748,"halstead":{"bugs":4.21,"difficulty":100.926,"effort":1274589.74,"length":1665,"time":70810.541,"vocabulary":192,"volume":12628.963,"operands":{"distinct":162,"total":1090,"identifiers":["__stripped__"]},"operators":{"distinct":30,"total":575,"identifiers":["__stripped__"]}},"params":56,"sloc":{"logical":163,"physical":283}}},"functions":[{"cyclomatic":1,"cyclomaticDensity":33.333,"halstead":{"bugs":0.043,"difficulty":12,"effort":1553.401,"length":34,"time":86.3,"vocabulary":14,"volume":129.45,"operands":{"distinct":6,"total":18,"identifiers":["__stripped__"]},"operators":{"distinct":8,"total":16,"identifiers":["__stripped__"]}},"params":2,"sloc":{"logical":3,"physical":5},"errors":[],"lineEnd":33,"lineStart":29,"name":"safeAdd","complexity":{"cyclomatic":1,"sloc":{"logical":3,"physical":5},"halstead":{"bugs":0.043,"difficulty":12,"effort":1553.401,"length":34,"time":86.3,"vocabulary":14,"volume":129.45,"operands":{"distinct":6,"total":18,"identifiers":["__stripped__"]},"operators":{"distinct":8,"total":16,"identifiers":["__stripped__"]}}},"line":29},{"cyclomatic":1,"cyclomaticDensity":100,"halstead":{"bugs":0.012,"difficulty":5.833,"effort":210,"length":12,"time":11.667,"vocabulary":8,"volume":36,"operands":{"distinct":3,"total":7,"identifiers":["__stripped__"]},"operators":{"distinct":5,"total":5,"identifiers":["__stripped__"]}},"params":2,"sloc":{"logical":1,"physical":3},"errors":[],"lineEnd":40,"lineStart":38,"name":"bitRotateLeft","complexity":{"cyclomatic":1,"sloc":{"logical":1,"physical":3},"halstead":{"bugs":0.012,"difficulty":5.833,"effort":210,"length":12,"time":11.667,"vocabulary":8,"volume":36,"operands":{"distinct":3,"total":7,"identifiers":["__stripped__"]},"operators":{"distinct":5,"total":5,"identifiers":["__stripped__"]}}},"line":38},{"cyclomatic":1,"cyclomaticDensity":100,"halstead":{"bugs":0.025,"difficulty":2.125,"effort":162.359,"length":23,"time":9.02,"vocabulary":10,"volume":76.404,"operands":{"distinct":8,"total":17,"identifiers":["__stripped__"]},"operators":{"distinct":2,"total":6,"identifiers":["__stripped__"]}},"params":6,"sloc":{"logical":1,"physical":3},"errors":[],"lineEnd":47,"lineStart":45,"name":"md5cmn","complexity":{"cyclomatic":1,"sloc":{"logical":1,"physical":3},"halstead":{"bugs":0.025,"difficulty":2.125,"effort":162.359,"length":23,"time":9.02,"vocabulary":10,"volume":76.404,"operands":{"distinct":8,"total":17,"identifiers":["__stripped__"]},"operators":{"distinct":2,"total":6,"identifiers":["__stripped__"]}}},"line":45},{"cyclomatic":1,"cyclomaticDensity":100,"halstead":{"bugs":0.028,"difficulty":5.313,"effort":452.147,"length":23,"time":25.119,"vocabulary":13,"volume":85.11,"operands":{"distinct":8,"total":17,"identifiers":["__stripped__"]},"operators":{"distinct":5,"total":6,"identifiers":["__stripped__"]}},"params":7,"sloc":{"logical":1,"physical":3},"errors":[],"lineEnd":50,"lineStart":48,"name":"md5ff","complexity":{"cyclomatic":1,"sloc":{"logical":1,"physical":3},"halstead":{"bugs":0.028,"difficulty":5.313,"effort":452.147,"length":23,"time":25.119,"vocabulary":13,"volume":85.11,"operands":{"distinct":8,"total":17,"identifiers":["__stripped__"]},"operators":{"distinct":5,"total":6,"identifiers":["__stripped__"]}}},"line":48},{"cyclomatic":1,"cyclomaticDensity":100,"halstead":{"bugs":0.028,"difficulty":5.313,"effort":452.147,"length":23,"time":25.119,"vocabulary":13,"volume":85.11,"operands":{"distinct":8,"total":17,"identifiers":["__stripped__"]},"operators":{"distinct":5,"total":6,"identifiers":["__stripped__"]}},"params":7,"sloc":{"logical":1,"physical":3},"errors":[],"lineEnd":53,"lineStart":51,"name":"md5gg","complexity":{"cyclomatic":1,"sloc":{"logical":1,"physical":3},"halstead":{"bugs":0.028,"difficulty":5.313,"effort":452.147,"length":23,"time":25.119,"vocabulary":13,"volume":85.11,"operands":{"distinct":8,"total":17,"identifiers":["__stripped__"]},"operators":{"distinct":5,"total":6,"identifiers":["__stripped__"]}}},"line":51},{"cyclomatic":1,"cyclomaticDensity":100,"halstead":{"bugs":0.023,"difficulty":3,"effort":207.566,"length":20,"time":11.531,"vocabulary":11,"volume":69.189,"operands":{"distinct":8,"total":16,"identifiers":["__stripped__"]},"operators":{"distinct":3,"total":4,"identifiers":["__stripped__"]}},"params":7,"sloc":{"logical":1,"physical":3},"errors":[],"lineEnd":56,"lineStart":54,"name":"md5hh","complexity":{"cyclomatic":1,"sloc":{"logical":1,"physical":3},"halstead":{"bugs":0.023,"difficulty":3,"effort":207.566,"length":20,"time":11.531,"vocabulary":11,"volume":69.189,"operands":{"distinct":8,"total":16,"identifiers":["__stripped__"]},"operators":{"distinct":3,"total":4,"identifiers":["__stripped__"]}}},"line":54},{"cyclomatic":1,"cyclomaticDensity":100,"halstead":{"bugs":0.026,"difficulty":5,"effort":388.546,"length":21,"time":21.586,"vocabulary":13,"volume":77.709,"operands":{"distinct":8,"total":16,"identifiers":["__stripped__"]},"operators":{"distinct":5,"total":5,"identifiers":["__stripped__"]}},"params":7,"sloc":{"logical":1,"physical":3},"errors":[],"lineEnd":59,"lineStart":57,"name":"md5ii","complexity":{"cyclomatic":1,"sloc":{"logical":1,"physical":3},"halstead":{"bugs":0.026,"difficulty":5,"effort":388.546,"length":21,"time":21.586,"vocabulary":13,"volume":77.709,"operands":{"distinct":8,"total":16,"identifiers":["__stripped__"]},"operators":{"distinct":5,"total":5,"identifiers":["__stripped__"]}}},"line":57},{"cyclomatic":2,"cyclomaticDensity":2.353,"halstead":{"bugs":2.579,"difficulty":58.959,"effort":456135.471,"length":1107,"time":25340.859,"vocabulary":127,"volume":7736.474,"operands":{"distinct":110,"total":763,"identifiers":["__stripped__"]},"operators":{"distinct":17,"total":344,"identifiers":["__stripped__"]}},"params":2,"sloc":{"logical":85,"physical":96},"errors":[],"lineEnd":159,"lineStart":64,"name":"binlMD5","complexity":{"cyclomatic":2,"sloc":{"logical":85,"physical":96},"halstead":{"bugs":2.579,"difficulty":58.959,"effort":456135.471,"length":1107,"time":25340.859,"vocabulary":127,"volume":7736.474,"operands":{"distinct":110,"total":763,"identifiers":["__stripped__"]},"operators":{"distinct":17,"total":344,"identifiers":["__stripped__"]}}},"line":64},{"cyclomatic":2,"cyclomaticDensity":33.333,"halstead":{"bugs":0.07,"difficulty":12.923,"effort":2703.702,"length":44,"time":150.206,"vocabulary":27,"volume":209.215,"operands":{"distinct":13,"total":24,"identifiers":["__stripped__"]},"operators":{"distinct":14,"total":20,"identifiers":["__stripped__"]}},"params":1,"sloc":{"logical":6,"physical":9},"errors":[],"lineEnd":172,"lineStart":164,"name":"binl2rstr","complexity":{"cyclomatic":2,"sloc":{"logical":6,"physical":9},"halstead":{"bugs":0.07,"difficulty":12.923,"effort":2703.702,"length":44,"time":150.206,"vocabulary":27,"volume":209.215,"operands":{"distinct":13,"total":24,"identifiers":["__stripped__"]},"operators":{"distinct":14,"total":20,"identifiers":["__stripped__"]}}},"line":164},{"cyclomatic":3,"cyclomaticDensity":33.333,"halstead":{"bugs":0.122,"difficulty":24.286,"effort":8903.399,"length":74,"time":494.633,"vocabulary":31,"volume":366.611,"operands":{"distinct":14,"total":40,"identifiers":["__stripped__"]},"operators":{"distinct":17,"total":34,"identifiers":["__stripped__"]}},"params":1,"sloc":{"logical":9,"physical":13},"errors":[],"lineEnd":190,"lineStart":178,"name":"rstr2binl","complexity":{"cyclomatic":3,"sloc":{"logical":9,"physical":13},"halstead":{"bugs":0.122,"difficulty":24.286,"effort":8903.399,"length":74,"time":494.633,"vocabulary":31,"volume":366.611,"operands":{"distinct":14,"total":40,"identifiers":["__stripped__"]},"operators":{"distinct":17,"total":34,"identifiers":["__stripped__"]}}},"line":178},{"cyclomatic":1,"cyclomaticDensity":100,"halstead":{"bugs":0.016,"difficulty":2.667,"effort":124.019,"length":14,"time":6.89,"vocabulary":10,"volume":46.507,"operands":{"distinct":6,"total":8,"identifiers":["__stripped__"]},"operators":{"distinct":4,"total":6,"identifiers":["__stripped__"]}},"params":1,"sloc":{"logical":1,"physical":3},"errors":[],"lineEnd":197,"lineStart":195,"name":"rstrMD5","complexity":{"cyclomatic":1,"sloc":{"logical":1,"physical":3},"halstead":{"bugs":0.016,"difficulty":2.667,"effort":124.019,"length":14,"time":6.89,"vocabulary":10,"volume":46.507,"operands":{"distinct":6,"total":8,"identifiers":["__stripped__"]},"operators":{"distinct":4,"total":6,"identifiers":["__stripped__"]}}},"line":195},{"cyclomatic":3,"cyclomaticDensity":23.077,"halstead":{"bugs":0.179,"difficulty":17.818,"effort":9580.341,"length":104,"time":532.241,"vocabulary":36,"volume":537.672,"operands":{"distinct":22,"total":56,"identifiers":["__stripped__"]},"operators":{"distinct":14,"total":48,"identifiers":["__stripped__"]}},"params":2,"sloc":{"logical":13,"physical":17},"errors":[],"lineEnd":218,"lineStart":202,"name":"rstrHMACMD5","complexity":{"cyclomatic":3,"sloc":{"logical":13,"physical":17},"halstead":{"bugs":0.179,"difficulty":17.818,"effort":9580.341,"length":104,"time":532.241,"vocabulary":36,"volume":537.672,"operands":{"distinct":22,"total":56,"identifiers":["__stripped__"]},"operators":{"distinct":14,"total":48,"identifiers":["__stripped__"]}}},"line":202},{"cyclomatic":2,"cyclomaticDensity":25,"halstead":{"bugs":0.082,"difficulty":11.393,"effort":2804.06,"length":53,"time":155.781,"vocabulary":25,"volume":246.124,"operands":{"distinct":14,"total":29,"identifiers":["__stripped__"]},"operators":{"distinct":11,"total":24,"identifiers":["__stripped__"]}},"params":1,"sloc":{"logical":8,"physical":11},"errors":[],"lineEnd":233,"lineStart":223,"name":"rstr2hex","complexity":{"cyclomatic":2,"sloc":{"logical":8,"physical":11},"halstead":{"bugs":0.082,"difficulty":11.393,"effort":2804.06,"length":53,"time":155.781,"vocabulary":25,"volume":246.124,"operands":{"distinct":14,"total":29,"identifiers":["__stripped__"]},"operators":{"distinct":11,"total":24,"identifiers":["__stripped__"]}}},"line":223},{"cyclomatic":1,"cyclomaticDensity":100,"halstead":{"bugs":0.005,"difficulty":1.333,"effort":21.671,"length":7,"time":1.204,"vocabulary":5,"volume":16.253,"operands":{"distinct":3,"total":4,"identifiers":["__stripped__"]},"operators":{"distinct":2,"total":3,"identifiers":["__stripped__"]}},"params":1,"sloc":{"logical":1,"physical":3},"errors":[],"lineEnd":240,"lineStart":238,"name":"str2rstrUTF8","complexity":{"cyclomatic":1,"sloc":{"logical":1,"physical":3},"halstead":{"bugs":0.005,"difficulty":1.333,"effort":21.671,"length":7,"time":1.204,"vocabulary":5,"volume":16.253,"operands":{"distinct":3,"total":4,"identifiers":["__stripped__"]},"operators":{"distinct":2,"total":3,"identifiers":["__stripped__"]}}},"line":238},{"cyclomatic":1,"cyclomaticDensity":100,"halstead":{"bugs":0.005,"difficulty":1.333,"effort":21.671,"length":7,"time":1.204,"vocabulary":5,"volume":16.253,"operands":{"distinct":3,"total":4,"identifiers":["__stripped__"]},"operators":{"distinct":2,"total":3,"identifiers":["__stripped__"]}},"params":1,"sloc":{"logical":1,"physical":3},"errors":[],"lineEnd":247,"lineStart":245,"name":"rawMD5","complexity":{"cyclomatic":1,"sloc":{"logical":1,"physical":3},"halstead":{"bugs":0.005,"difficulty":1.333,"effort":21.671,"length":7,"time":1.204,"vocabulary":5,"volume":16.253,"operands":{"distinct":3,"total":4,"identifiers":["__stripped__"]},"operators":{"distinct":2,"total":3,"identifiers":["__stripped__"]}}},"line":245},{"cyclomatic":1,"cyclomaticDensity":100,"halstead":{"bugs":0.005,"difficulty":1.333,"effort":21.671,"length":7,"time":1.204,"vocabulary":5,"volume":16.253,"operands":{"distinct":3,"total":4,"identifiers":["__stripped__"]},"operators":{"distinct":2,"total":3,"identifiers":["__stripped__"]}},"params":1,"sloc":{"logical":1,"physical":3},"errors":[],"lineEnd":250,"lineStart":248,"name":"hexMD5","complexity":{"cyclomatic":1,"sloc":{"logical":1,"physical":3},"halstead":{"bugs":0.005,"difficulty":1.333,"effort":21.671,"length":7,"time":1.204,"vocabulary":5,"volume":16.253,"operands":{"distinct":3,"total":4,"identifiers":["__stripped__"]},"operators":{"distinct":2,"total":3,"identifiers":["__stripped__"]}}},"line":248},{"cyclomatic":1,"cyclomaticDensity":100,"halstead":{"bugs":0.009,"difficulty":1.75,"effort":49.761,"length":11,"time":2.764,"vocabulary":6,"volume":28.435,"operands":{"distinct":4,"total":7,"identifiers":["__stripped__"]},"operators":{"distinct":2,"total":4,"identifiers":["__stripped__"]}},"params":2,"sloc":{"logical":1,"physical":3},"errors":[],"lineEnd":253,"lineStart":251,"name":"rawHMACMD5","complexity":{"cyclomatic":1,"sloc":{"logical":1,"physical":3},"halstead":{"bugs":0.009,"difficulty":1.75,"effort":49.761,"length":11,"time":2.764,"vocabulary":6,"volume":28.435,"operands":{"distinct":4,"total":7,"identifiers":["__stripped__"]},"operators":{"distinct":2,"total":4,"identifiers":["__stripped__"]}}},"line":251},{"cyclomatic":1,"cyclomaticDensity":100,"halstead":{"bugs":0.008,"difficulty":1.5,"effort":34.897,"length":9,"time":1.939,"vocabulary":6,"volume":23.265,"operands":{"distinct":4,"total":6,"identifiers":["__stripped__"]},"operators":{"distinct":2,"total":3,"identifiers":["__stripped__"]}},"params":2,"sloc":{"logical":1,"physical":3},"errors":[],"lineEnd":256,"lineStart":254,"name":"hexHMACMD5","complexity":{"cyclomatic":1,"sloc":{"logical":1,"physical":3},"halstead":{"bugs":0.008,"difficulty":1.5,"effort":34.897,"length":9,"time":1.939,"vocabulary":6,"volume":23.265,"operands":{"distinct":4,"total":6,"identifiers":["__stripped__"]},"operators":{"distinct":2,"total":3,"identifiers":["__stripped__"]}}},"line":254},{"cyclomatic":4,"cyclomaticDensity":57.143,"halstead":{"bugs":0.035,"difficulty":4.571,"effort":474.436,"length":30,"time":26.358,"vocabulary":11,"volume":103.783,"operands":{"distinct":7,"total":16,"identifiers":["__stripped__"]},"operators":{"distinct":4,"total":14,"identifiers":["__stripped__"]}},"params":3,"sloc":{"logical":7,"physical":12},"errors":[],"lineEnd":269,"lineStart":258,"name":"md5","complexity":{"cyclomatic":4,"sloc":{"logical":7,"physical":12},"halstead":{"bugs":0.035,"difficulty":4.571,"effort":474.436,"length":30,"time":26.358,"vocabulary":11,"volume":103.783,"operands":{"distinct":7,"total":16,"identifiers":["__stripped__"]},"operators":{"distinct":4,"total":14,"identifiers":["__stripped__"]}}},"line":258}]},"eslint":{"messages":[{"severity":"error","line":23,"column":15,"message":"Missing semicolon.","fix":{"range":[632,632],"text":";"}},{"severity":"error","line":30,"column":42,"message":"Missing semicolon.","fix":{"range":[844,844],"text":";"}},{"severity":"error","line":31,"column":50,"message":"Missing semicolon.","fix":{"range":[895,895],"text":";"}},{"severity":"error","line":32,"column":40,"message":"Missing semicolon.","fix":{"range":[936,936],"text":";"}},{"severity":"error","line":39,"column":47,"message":"Missing semicolon.","fix":{"range":[1091,1091],"text":";"}},{"severity":"error","line":46,"column":79,"message":"Missing semicolon.","fix":{"range":[1307,1307],"text":";"}},{"severity":"error","line":49,"column":53,"message":"Missing semicolon.","fix":{"range":[1408,1408],"text":";"}},{"severity":"error","line":52,"column":53,"message":"Missing semicolon.","fix":{"range":[1509,1509],"text":";"}},{"severity":"error","line":55,"column":44,"message":"Missing semicolon.","fix":{"range":[1601,1601],"text":";"}},{"severity":"error","line":58,"column":47,"message":"Missing semicolon.","fix":{"range":[1696,1696],"text":";"}},{"severity":"error","line":66,"column":38,"message":"Missing semicolon.","fix":{"range":[1888,1888],"text":";"}},{"severity":"error","line":67,"column":42,"message":"Missing semicolon.","fix":{"range":[1931,1931],"text":";"}},{"severity":"error","line":69,"column":10,"message":"Missing semicolon.","fix":{"range":[1944,1944],"text":";"}},{"severity":"error","line":70,"column":13,"message":"Missing semicolon.","fix":{"range":[1958,1958],"text":";"}},{"severity":"error","line":71,"column":13,"message":"Missing semicolon.","fix":{"range":[1972,1972],"text":";"}},{"severity":"error","line":72,"column":13,"message":"Missing semicolon.","fix":{"range":[1986,1986],"text":";"}},{"severity":"error","line":73,"column":13,"message":"Missing semicolon.","fix":{"range":[2000,2000],"text":";"}},{"severity":"error","line":74,"column":23,"message":"Missing semicolon.","fix":{"range":[2024,2024],"text":";"}},{"severity":"error","line":75,"column":23,"message":"Missing semicolon.","fix":{"range":[2048,2048],"text":";"}},{"severity":"error","line":76,"column":24,"message":"Missing semicolon.","fix":{"range":[2073,2073],"text":";"}},{"severity":"error","line":77,"column":22,"message":"Missing semicolon.","fix":{"range":[2096,2096],"text":";"}},{"severity":"error","line":80,"column":15,"message":"Missing semicolon.","fix":{"range":[2156,2156],"text":";"}},{"severity":"error","line":81,"column":15,"message":"Missing semicolon.","fix":{"range":[2172,2172],"text":";"}},{"severity":"error","line":82,"column":15,"message":"Missing semicolon.","fix":{"range":[2188,2188],"text":";"}},{"severity":"error","line":83,"column":15,"message":"Missing semicolon.","fix":{"range":[2204,2204],"text":";"}},{"severity":"error","line":85,"column":49,"message":"Missing semicolon.","fix":{"range":[2256,2256],"text":";"}},{"severity":"error","line":86,"column":54,"message":"Missing semicolon.","fix":{"range":[2311,2311],"text":";"}},{"severity":"error","line":87,"column":53,"message":"Missing semicolon.","fix":{"range":[2365,2365],"text":";"}},{"severity":"error","line":88,"column":55,"message":"Missing semicolon.","fix":{"range":[2421,2421],"text":";"}},{"severity":"error","line":89,"column":53,"message":"Missing semicolon.","fix":{"range":[2475,2475],"text":";"}},{"severity":"error","line":90,"column":54,"message":"Missing semicolon.","fix":{"range":[2530,2530],"text":";"}},{"severity":"error","line":91,"column":55,"message":"Missing semicolon.","fix":{"range":[2586,2586],"text":";"}},{"severity":"error","line":92,"column":53,"message":"Missing semicolon.","fix":{"range":[2640,2640],"text":";"}},{"severity":"error","line":93,"column":53,"message":"Missing semicolon.","fix":{"range":[2694,2694],"text":";"}},{"severity":"error","line":94,"column":55,"message":"Missing semicolon.","fix":{"range":[2750,2750],"text":";"}},{"severity":"error","line":95,"column":51,"message":"Missing semicolon.","fix":{"range":[2802,2802],"text":";"}},{"severity":"error","line":96,"column":56,"message":"Missing semicolon.","fix":{"range":[2859,2859],"text":";"}},{"severity":"error","line":97,"column":54,"message":"Missing semicolon.","fix":{"range":[2914,2914],"text":";"}},{"severity":"error","line":98,"column":54,"message":"Missing semicolon.","fix":{"range":[2969,2969],"text":";"}},{"severity":"error","line":99,"column":56,"message":"Missing semicolon.","fix":{"range":[3026,3026],"text":";"}},{"severity":"error","line":100,"column":55,"message":"Missing semicolon.","fix":{"range":[3082,3082],"text":";"}},{"severity":"error","line":102,"column":53,"message":"Missing semicolon.","fix":{"range":[3138,3138],"text":";"}},{"severity":"error","line":103,"column":54,"message":"Missing semicolon.","fix":{"range":[3193,3193],"text":";"}},{"severity":"error","line":104,"column":54,"message":"Missing semicolon.","fix":{"range":[3248,3248],"text":";"}},{"severity":"error","line":105,"column":50,"message":"Missing semicolon.","fix":{"range":[3299,3299],"text":";"}},{"severity":"error","line":106,"column":53,"message":"Missing semicolon.","fix":{"range":[3353,3353],"text":";"}},{"severity":"error","line":107,"column":52,"message":"Missing semicolon.","fix":{"range":[3406,3406],"text":";"}},{"severity":"error","line":108,"column":55,"message":"Missing semicolon.","fix":{"range":[3462,3462],"text":";"}},{"severity":"error","line":109,"column":54,"message":"Missing semicolon.","fix":{"range":[3517,3517],"text":";"}},{"severity":"error","line":110,"column":52,"message":"Missing semicolon.","fix":{"range":[3570,3570],"text":";"}},{"severity":"error","line":111,"column":55,"message":"Missing semicolon.","fix":{"range":[3626,3626],"text":";"}},{"severity":"error","line":112,"column":54,"message":"Missing semicolon.","fix":{"range":[3681,3681],"text":";"}},{"severity":"error","line":113,"column":54,"message":"Missing semicolon.","fix":{"range":[3736,3736],"text":";"}},{"severity":"error","line":114,"column":55,"message":"Missing semicolon.","fix":{"range":[3792,3792],"text":";"}},{"severity":"error","line":115,"column":52,"message":"Missing semicolon.","fix":{"range":[3845,3845],"text":";"}},{"severity":"error","line":116,"column":54,"message":"Missing semicolon.","fix":{"range":[3900,3900],"text":";"}},{"severity":"error","line":117,"column":56,"message":"Missing semicolon.","fix":{"range":[3957,3957],"text":";"}},{"severity":"error","line":119,"column":50,"message":"Missing semicolon.","fix":{"range":[4010,4010],"text":";"}},{"severity":"error","line":120,"column":55,"message":"Missing semicolon.","fix":{"range":[4066,4066],"text":";"}},{"severity":"error","line":121,"column":55,"message":"Missing semicolon.","fix":{"range":[4122,4122],"text":";"}},{"severity":"error","line":122,"column":54,"message":"Missing semicolon.","fix":{"range":[4177,4177],"text":";"}},{"severity":"error","line":123,"column":54,"message":"Missing semicolon.","fix":{"range":[4232,4232],"text":";"}},{"severity":"error","line":124,"column":54,"message":"Missing semicolon.","fix":{"range":[4287,4287],"text":";"}},{"severity":"error","line":125,"column":54,"message":"Missing semicolon.","fix":{"range":[4342,4342],"text":";"}},{"severity":"error","line":126,"column":56,"message":"Missing semicolon.","fix":{"range":[4399,4399],"text":";"}},{"severity":"error","line":127,"column":53,"message":"Missing semicolon.","fix":{"range":[4453,4453],"text":";"}},{"severity":"error","line":128,"column":50,"message":"Missing semicolon.","fix":{"range":[4504,4504],"text":";"}},{"severity":"error","line":129,"column":54,"message":"Missing semicolon.","fix":{"range":[4559,4559],"text":";"}},{"severity":"error","line":130,"column":52,"message":"Missing semicolon.","fix":{"range":[4612,4612],"text":";"}},{"severity":"error","line":131,"column":53,"message":"Missing semicolon.","fix":{"range":[4666,4666],"text":";"}},{"severity":"error","line":132,"column":55,"message":"Missing semicolon.","fix":{"range":[4722,4722],"text":";"}},{"severity":"error","line":133,"column":54,"message":"Missing semicolon.","fix":{"range":[4777,4777],"text":";"}},{"severity":"error","line":134,"column":54,"message":"Missing semicolon.","fix":{"range":[4832,4832],"text":";"}},{"severity":"error","line":136,"column":49,"message":"Missing semicolon.","fix":{"range":[4884,4884],"text":";"}},{"severity":"error","line":137,"column":54,"message":"Missing semicolon.","fix":{"range":[4939,4939],"text":";"}},{"severity":"error","line":138,"column":56,"message":"Missing semicolon.","fix":{"range":[4996,4996],"text":";"}},{"severity":"error","line":139,"column":53,"message":"Missing semicolon.","fix":{"range":[5050,5050],"text":";"}},{"severity":"error","line":140,"column":54,"message":"Missing semicolon.","fix":{"range":[5105,5105],"text":";"}},{"severity":"error","line":141,"column":55,"message":"Missing semicolon.","fix":{"range":[5161,5161],"text":";"}},{"severity":"error","line":142,"column":53,"message":"Missing semicolon.","fix":{"range":[5215,5215],"text":";"}},{"severity":"error","line":143,"column":55,"message":"Missing semicolon.","fix":{"range":[5271,5271],"text":";"}},{"severity":"error","line":144,"column":53,"message":"Missing semicolon.","fix":{"range":[5325,5325],"text":";"}},{"severity":"error","line":145,"column":54,"message":"Missing semicolon.","fix":{"range":[5380,5380],"text":";"}},{"severity":"error","line":146,"column":55,"message":"Missing semicolon.","fix":{"range":[5436,5436],"text":";"}},{"severity":"error","line":147,"column":55,"message":"Missing semicolon.","fix":{"range":[5492,5492],"text":";"}},{"severity":"error","line":148,"column":53,"message":"Missing semicolon.","fix":{"range":[5546,5546],"text":";"}},{"severity":"error","line":149,"column":56,"message":"Missing semicolon.","fix":{"range":[5603,5603],"text":";"}},{"severity":"error","line":150,"column":53,"message":"Missing semicolon.","fix":{"range":[5657,5657],"text":";"}},{"severity":"error","line":151,"column":54,"message":"Missing semicolon.","fix":{"range":[5712,5712],"text":";"}},{"severity":"error","line":153,"column":27,"message":"Missing semicolon.","fix":{"range":[5742,5742],"text":";"}},{"severity":"error","line":154,"column":27,"message":"Missing semicolon.","fix":{"range":[5770,5770],"text":";"}},{"severity":"error","line":155,"column":27,"message":"Missing semicolon.","fix":{"range":[5798,5798],"text":";"}},{"severity":"error","line":156,"column":27,"message":"Missing semicolon.","fix":{"range":[5826,5826],"text":";"}},{"severity":"error","line":158,"column":24,"message":"Missing semicolon.","fix":{"range":[5858,5858],"text":";"}},{"severity":"error","line":165,"column":10,"message":"Missing semicolon.","fix":{"range":[5977,5977],"text":";"}},{"severity":"error","line":166,"column":20,"message":"Missing semicolon.","fix":{"range":[5998,5998],"text":";"}},{"severity":"error","line":167,"column":37,"message":"Missing semicolon.","fix":{"range":[6036,6036],"text":";"}},{"severity":"error","line":169,"column":73,"message":"Missing semicolon.","fix":{"range":[6151,6151],"text":";"}},{"severity":"error","line":171,"column":18,"message":"Missing semicolon.","fix":{"range":[6177,6177],"text":";"}},{"severity":"error","line":179,"column":10,"message":"Missing semicolon.","fix":{"range":[6360,6360],"text":";"}},{"severity":"error","line":180,"column":20,"message":"Missing semicolon.","fix":{"range":[6381,6381],"text":";"}},{"severity":"error","line":181,"column":48,"message":"Missing semicolon.","fix":{"range":[6430,6430],"text":";"}},{"severity":"error","line":183,"column":20,"message":"Missing semicolon.","fix":{"range":[6497,6497],"text":";"}},{"severity":"error","line":185,"column":35,"message":"Missing semicolon.","fix":{"range":[6540,6540],"text":";"}},{"severity":"error","line":187,"column":69,"message":"Missing semicolon.","fix":{"range":[6650,6650],"text":";"}},{"severity":"error","line":189,"column":18,"message":"Missing semicolon.","fix":{"range":[6676,6676],"text":";"}},{"severity":"error","line":196,"column":58,"message":"Missing semicolon.","fix":{"range":[6819,6819],"text":";"}},{"severity":"error","line":203,"column":10,"message":"Missing semicolon.","fix":{"range":[6953,6953],"text":";"}},{"severity":"error","line":204,"column":30,"message":"Missing semicolon.","fix":{"range":[6984,6984],"text":";"}},{"severity":"error","line":205,"column":18,"message":"Missing semicolon.","fix":{"range":[7003,7003],"text":";"}},{"severity":"error","line":206,"column":18,"message":"Missing semicolon.","fix":{"range":[7022,7022],"text":";"}},{"severity":"error","line":207,"column":13,"message":"Missing semicolon.","fix":{"range":[7036,7036],"text":";"}},{"severity":"error","line":208,"column":36,"message":"Missing semicolon.","fix":{"range":[7073,7073],"text":";"}},{"severity":"error","line":210,"column":43,"message":"Missing semicolon.","fix":{"range":[7146,7146],"text":";"}},{"severity":"error","line":213,"column":37,"message":"Missing semicolon.","fix":{"range":[7226,7226],"text":";"}},{"severity":"error","line":214,"column":37,"message":"Missing semicolon.","fix":{"range":[7264,7264],"text":";"}},{"severity":"error","line":216,"column":72,"message":"Missing semicolon.","fix":{"range":[7344,7344],"text":";"}},{"severity":"error","line":217,"column":60,"message":"Missing semicolon.","fix":{"range":[7405,7405],"text":";"}},{"severity":"error","line":224,"column":36,"message":"Missing semicolon.","fix":{"range":[7534,7534],"text":";"}},{"severity":"error","line":225,"column":20,"message":"Missing semicolon.","fix":{"range":[7555,7555],"text":";"}},{"severity":"error","line":226,"column":10,"message":"Missing semicolon.","fix":{"range":[7566,7566],"text":";"}},{"severity":"error","line":227,"column":10,"message":"Missing semicolon.","fix":{"range":[7577,7577],"text":";"}},{"severity":"error","line":229,"column":30,"message":"Missing semicolon.","fix":{"range":[7653,7653],"text":";"}},{"severity":"error","line":230,"column":74,"message":"Missing semicolon.","fix":{"range":[7728,7728],"text":";"}},{"severity":"error","line":232,"column":18,"message":"Missing semicolon.","fix":{"range":[7754,7754],"text":";"}},{"severity":"error","line":239,"column":47,"message":"Missing semicolon.","fix":{"range":[7886,7886],"text":";"}},{"severity":"error","line":246,"column":36,"message":"Missing semicolon.","fix":{"range":[8039,8039],"text":";"}},{"severity":"error","line":249,"column":31,"message":"Missing semicolon.","fix":{"range":[8101,8101],"text":";"}},{"severity":"error","line":252,"column":57,"message":"Missing semicolon.","fix":{"range":[8196,8196],"text":";"}},{"severity":"error","line":255,"column":38,"message":"Missing semicolon.","fix":{"range":[8272,8272],"text":";"}},{"severity":"error","line":261,"column":30,"message":"Missing semicolon.","fix":{"range":[8383,8383],"text":";"}},{"severity":"error","line":263,"column":28,"message":"Missing semicolon.","fix":{"range":[8421,8421],"text":";"}},{"severity":"error","line":266,"column":37,"message":"Missing semicolon.","fix":{"range":[8483,8483],"text":";"}},{"severity":"error","line":268,"column":35,"message":"Missing semicolon.","fix":{"range":[8526,8526],"text":";"}}]}}