{"info":{"file":"page/airport-transportation/airport-transportation.js","fileShort":"page/airport-transportation/airport-transportation.js","fileSafe":"page_airport_transportation_airport_transportation_js","link":"files/page_airport_transportation_airport_transportation_js/index.html"},"complexity":{"methodAggregate":{"cyclomatic":238,"cyclomaticDensity":24.612,"halstead":{"bugs":17.386,"difficulty":126.757,"effort":6611476.052,"length":5854,"time":367304.225,"vocabulary":481,"volume":52158.514,"operands":{"distinct":441,"total":2795,"identifiers":["__stripped__"]},"operators":{"distinct":40,"total":3059,"identifiers":["__stripped__"]}},"params":19,"sloc":{"logical":967,"physical":1438}},"settings":{"commonjs":false,"forin":false,"logicalor":true,"switchcase":true,"trycatch":false,"newmi":true},"classes":[],"dependencies":[{"line":2,"path":"../../common/mapView/mapView.js","type":"esm"},{"line":3,"path":"../../common/network/requests/ReverseGeoRequest.js","type":"esm"},{"line":4,"path":"../../common/lib/deepPath.js","type":"esm"},{"line":5,"path":"../../common/network/requests/CarNearbyRequest.js","type":"esm"},{"line":6,"path":"../../common/network/requests/RecommendSpotsRequest.js","type":"esm"},{"line":7,"path":"../../common/network/requests/FlightInformationQueryRequire.js","type":"esm"},{"line":8,"path":"../../common/GlobalConfigHelper.js","type":"esm"},{"line":9,"path":"../../common/api/api.js","type":"esm"},{"line":10,"path":"../../service/messagecenter/TaxiMessageService.js","type":"esm"},{"line":11,"path":"../../common/TaxiLog.js","type":"esm"},{"line":12,"path":"../../service/datacenter/DataHelper.js","type":"esm"},{"line":13,"path":"../../common/util/PickupCarHelper.js","type":"esm"},{"line":14,"path":"../../common/network/requests/CarTypeRequest.js","type":"esm"}],"errors":[],"lineEnd":1438,"lineStart":1,"maintainability":61.716,"methods":[{"cyclomatic":1,"cyclomaticDensity":100,"halstead":{"bugs":0.014,"difficulty":2,"effort":82.418,"length":13,"time":4.579,"vocabulary":9,"volume":41.209,"operands":{"distinct":6,"total":8,"identifiers":["__stripped__"]},"operators":{"distinct":3,"total":5,"identifiers":["__stripped__"]}},"params":1,"sloc":{"logical":1,"physical":3},"errors":[],"lineEnd":272,"lineStart":270,"name":"<anonymous>","complexity":{"cyclomatic":1,"sloc":{"logical":1,"physical":3},"halstead":{"bugs":0.014,"difficulty":2,"effort":82.418,"length":13,"time":4.579,"vocabulary":9,"volume":41.209,"operands":{"distinct":6,"total":8,"identifiers":["__stripped__"]},"operators":{"distinct":3,"total":5,"identifiers":["__stripped__"]}}},"line":270},{"cyclomatic":1,"cyclomaticDensity":50,"halstead":{"bugs":0.008,"difficulty":2,"effort":48,"length":8,"time":2.667,"vocabulary":8,"volume":24,"operands":{"distinct":4,"total":4,"identifiers":["__stripped__"]},"operators":{"distinct":4,"total":4,"identifiers":["__stripped__"]}},"params":0,"sloc":{"logical":2,"physical":5},"errors":[],"lineEnd":434,"lineStart":430,"name":"<anonymous>","complexity":{"cyclomatic":1,"sloc":{"logical":2,"physical":5},"halstead":{"bugs":0.008,"difficulty":2,"effort":48,"length":8,"time":2.667,"vocabulary":8,"volume":24,"operands":{"distinct":4,"total":4,"identifiers":["__stripped__"]},"operators":{"distinct":4,"total":4,"identifiers":["__stripped__"]}}},"line":430},{"cyclomatic":1,"cyclomaticDensity":33.333,"halstead":{"bugs":0.018,"difficulty":4.8,"effort":265.684,"length":16,"time":14.76,"vocabulary":11,"volume":55.351,"operands":{"distinct":5,"total":8,"identifiers":["__stripped__"]},"operators":{"distinct":6,"total":8,"identifiers":["__stripped__"]}},"params":1,"sloc":{"logical":3,"physical":7},"errors":[],"lineEnd":469,"lineStart":463,"name":"<anonymous>","complexity":{"cyclomatic":1,"sloc":{"logical":3,"physical":7},"halstead":{"bugs":0.018,"difficulty":4.8,"effort":265.684,"length":16,"time":14.76,"vocabulary":11,"volume":55.351,"operands":{"distinct":5,"total":8,"identifiers":["__stripped__"]},"operators":{"distinct":6,"total":8,"identifiers":["__stripped__"]}}},"line":463},{"cyclomatic":1,"cyclomaticDensity":100,"halstead":{"bugs":0.005,"difficulty":2.25,"effort":31.346,"length":6,"time":1.741,"vocabulary":5,"volume":13.932,"operands":{"distinct":2,"total":3,"identifiers":["__stripped__"]},"operators":{"distinct":3,"total":3,"identifiers":["__stripped__"]}},"params":1,"sloc":{"logical":1,"physical":3},"errors":[],"lineEnd":468,"lineStart":466,"name":"<anonymous>","complexity":{"cyclomatic":1,"sloc":{"logical":1,"physical":3},"halstead":{"bugs":0.005,"difficulty":2.25,"effort":31.346,"length":6,"time":1.741,"vocabulary":5,"volume":13.932,"operands":{"distinct":2,"total":3,"identifiers":["__stripped__"]},"operators":{"distinct":3,"total":3,"identifiers":["__stripped__"]}}},"line":466},{"cyclomatic":1,"cyclomaticDensity":50,"halstead":{"bugs":0.008,"difficulty":2,"effort":48,"length":8,"time":2.667,"vocabulary":8,"volume":24,"operands":{"distinct":4,"total":4,"identifiers":["__stripped__"]},"operators":{"distinct":4,"total":4,"identifiers":["__stripped__"]}},"params":0,"sloc":{"logical":2,"physical":5},"errors":[],"lineEnd":490,"lineStart":486,"name":"<anonymous>","complexity":{"cyclomatic":1,"sloc":{"logical":2,"physical":5},"halstead":{"bugs":0.008,"difficulty":2,"effort":48,"length":8,"time":2.667,"vocabulary":8,"volume":24,"operands":{"distinct":4,"total":4,"identifiers":["__stripped__"]},"operators":{"distinct":4,"total":4,"identifiers":["__stripped__"]}}},"line":486},{"cyclomatic":6,"cyclomaticDensity":23.077,"halstead":{"bugs":0.193,"difficulty":17.182,"effort":9964.952,"length":114,"time":553.608,"vocabulary":34,"volume":579.971,"operands":{"distinct":22,"total":63,"identifiers":["__stripped__"]},"operators":{"distinct":12,"total":51,"identifiers":["__stripped__"]}},"params":1,"sloc":{"logical":26,"physical":36},"errors":[],"lineEnd":573,"lineStart":538,"name":"<anonymous>","complexity":{"cyclomatic":6,"sloc":{"logical":26,"physical":36},"halstead":{"bugs":0.193,"difficulty":17.182,"effort":9964.952,"length":114,"time":553.608,"vocabulary":34,"volume":579.971,"operands":{"distinct":22,"total":63,"identifiers":["__stripped__"]},"operators":{"distinct":12,"total":51,"identifiers":["__stripped__"]}}},"line":538},{"cyclomatic":2,"cyclomaticDensity":100,"halstead":{"bugs":0.026,"difficulty":3,"effort":234.413,"length":20,"time":13.023,"vocabulary":15,"volume":78.138,"operands":{"distinct":9,"total":9,"identifiers":["__stripped__"]},"operators":{"distinct":6,"total":11,"identifiers":["__stripped__"]}},"params":0,"sloc":{"logical":2,"physical":10},"errors":[],"lineEnd":591,"lineStart":582,"name":"<anonymous>","complexity":{"cyclomatic":2,"sloc":{"logical":2,"physical":10},"halstead":{"bugs":0.026,"difficulty":3,"effort":234.413,"length":20,"time":13.023,"vocabulary":15,"volume":78.138,"operands":{"distinct":9,"total":9,"identifiers":["__stripped__"]},"operators":{"distinct":6,"total":11,"identifiers":["__stripped__"]}}},"line":582},{"cyclomatic":1,"cyclomaticDensity":50,"halstead":{"bugs":0.017,"difficulty":2.5,"effort":126.797,"length":16,"time":7.044,"vocabulary":9,"volume":50.719,"operands":{"distinct":6,"total":10,"identifiers":["__stripped__"]},"operators":{"distinct":3,"total":6,"identifiers":["__stripped__"]}},"params":1,"sloc":{"logical":2,"physical":6},"errors":[],"lineEnd":589,"lineStart":584,"name":"<anonymous>","complexity":{"cyclomatic":1,"sloc":{"logical":2,"physical":6},"halstead":{"bugs":0.017,"difficulty":2.5,"effort":126.797,"length":16,"time":7.044,"vocabulary":9,"volume":50.719,"operands":{"distinct":6,"total":10,"identifiers":["__stripped__"]},"operators":{"distinct":3,"total":6,"identifiers":["__stripped__"]}}},"line":584},{"cyclomatic":7,"cyclomaticDensity":35,"halstead":{"bugs":0.261,"difficulty":27,"effort":21110.923,"length":145,"time":1172.829,"vocabulary":42,"volume":781.886,"operands":{"distinct":24,"total":72,"identifiers":["__stripped__"]},"operators":{"distinct":18,"total":73,"identifiers":["__stripped__"]}},"params":1,"sloc":{"logical":20,"physical":46},"errors":[],"lineEnd":739,"lineStart":694,"name":"<anonymous>","complexity":{"cyclomatic":7,"sloc":{"logical":20,"physical":46},"halstead":{"bugs":0.261,"difficulty":27,"effort":21110.923,"length":145,"time":1172.829,"vocabulary":42,"volume":781.886,"operands":{"distinct":24,"total":72,"identifiers":["__stripped__"]},"operators":{"distinct":18,"total":73,"identifiers":["__stripped__"]}}},"line":694},{"cyclomatic":1,"cyclomaticDensity":7.143,"halstead":{"bugs":0.089,"difficulty":3.173,"effort":848.882,"length":54,"time":47.16,"vocabulary":31,"volume":267.527,"operands":{"distinct":26,"total":33,"identifiers":["__stripped__"]},"operators":{"distinct":5,"total":21,"identifiers":["__stripped__"]}},"params":2,"sloc":{"logical":14,"physical":19},"errors":[],"lineEnd":734,"lineStart":716,"name":"<anonymous>","complexity":{"cyclomatic":1,"sloc":{"logical":14,"physical":19},"halstead":{"bugs":0.089,"difficulty":3.173,"effort":848.882,"length":54,"time":47.16,"vocabulary":31,"volume":267.527,"operands":{"distinct":26,"total":33,"identifiers":["__stripped__"]},"operators":{"distinct":5,"total":21,"identifiers":["__stripped__"]}}},"line":716},{"cyclomatic":3,"cyclomaticDensity":100,"halstead":{"bugs":0.045,"difficulty":7,"effort":952,"length":34,"time":52.889,"vocabulary":16,"volume":136,"operands":{"distinct":9,"total":18,"identifiers":["__stripped__"]},"operators":{"distinct":7,"total":16,"identifiers":["__stripped__"]}},"params":1,"sloc":{"logical":3,"physical":6},"errors":[],"lineEnd":767,"lineStart":762,"name":"<anonymous>","complexity":{"cyclomatic":3,"sloc":{"logical":3,"physical":6},"halstead":{"bugs":0.045,"difficulty":7,"effort":952,"length":34,"time":52.889,"vocabulary":16,"volume":136,"operands":{"distinct":9,"total":18,"identifiers":["__stripped__"]},"operators":{"distinct":7,"total":16,"identifiers":["__stripped__"]}}},"line":762},{"cyclomatic":10,"cyclomaticDensity":58.824,"halstead":{"bugs":0.253,"difficulty":16.571,"effort":12575.411,"length":139,"time":698.634,"vocabulary":44,"volume":758.861,"operands":{"distinct":28,"total":58,"identifiers":["__stripped__"]},"operators":{"distinct":16,"total":81,"identifiers":["__stripped__"]}},"params":1,"sloc":{"logical":17,"physical":24},"errors":[],"lineEnd":798,"lineStart":775,"name":"<anonymous>","complexity":{"cyclomatic":10,"sloc":{"logical":17,"physical":24},"halstead":{"bugs":0.253,"difficulty":16.571,"effort":12575.411,"length":139,"time":698.634,"vocabulary":44,"volume":758.861,"operands":{"distinct":28,"total":58,"identifiers":["__stripped__"]},"operators":{"distinct":16,"total":81,"identifiers":["__stripped__"]}}},"line":775},{"cyclomatic":1,"cyclomaticDensity":50,"halstead":{"bugs":0.008,"difficulty":2.5,"effort":60,"length":8,"time":3.333,"vocabulary":8,"volume":24,"operands":{"distinct":3,"total":3,"identifiers":["__stripped__"]},"operators":{"distinct":5,"total":5,"identifiers":["__stripped__"]}},"params":0,"sloc":{"logical":2,"physical":5},"errors":[],"lineEnd":809,"lineStart":805,"name":"<anonymous>","complexity":{"cyclomatic":1,"sloc":{"logical":2,"physical":5},"halstead":{"bugs":0.008,"difficulty":2.5,"effort":60,"length":8,"time":3.333,"vocabulary":8,"volume":24,"operands":{"distinct":3,"total":3,"identifiers":["__stripped__"]},"operators":{"distinct":5,"total":5,"identifiers":["__stripped__"]}}},"line":805},{"cyclomatic":10,"cyclomaticDensity":26.316,"halstead":{"bugs":0.437,"difficulty":20.953,"effort":27476.932,"length":222,"time":1526.496,"vocabulary":60,"volume":1311.33,"operands":{"distinct":43,"total":106,"identifiers":["__stripped__"]},"operators":{"distinct":17,"total":116,"identifiers":["__stripped__"]}},"params":1,"sloc":{"logical":38,"physical":79},"errors":[],"lineEnd":1021,"lineStart":943,"name":"<anonymous>","complexity":{"cyclomatic":10,"sloc":{"logical":38,"physical":79},"halstead":{"bugs":0.437,"difficulty":20.953,"effort":27476.932,"length":222,"time":1526.496,"vocabulary":60,"volume":1311.33,"operands":{"distinct":43,"total":106,"identifiers":["__stripped__"]},"operators":{"distinct":17,"total":116,"identifiers":["__stripped__"]}}},"line":943},{"cyclomatic":5,"cyclomaticDensity":38.462,"halstead":{"bugs":0.117,"difficulty":9.722,"effort":3411.887,"length":73,"time":189.549,"vocabulary":28,"volume":350.937,"operands":{"distinct":18,"total":35,"identifiers":["__stripped__"]},"operators":{"distinct":10,"total":38,"identifiers":["__stripped__"]}},"params":0,"sloc":{"logical":13,"physical":29},"errors":[],"lineEnd":1009,"lineStart":981,"name":"<anonymous>","complexity":{"cyclomatic":5,"sloc":{"logical":13,"physical":29},"halstead":{"bugs":0.117,"difficulty":9.722,"effort":3411.887,"length":73,"time":189.549,"vocabulary":28,"volume":350.937,"operands":{"distinct":18,"total":35,"identifiers":["__stripped__"]},"operators":{"distinct":10,"total":38,"identifiers":["__stripped__"]}}},"line":981},{"cyclomatic":2,"cyclomaticDensity":200,"halstead":{"bugs":0.009,"difficulty":3,"effort":77.549,"length":10,"time":4.308,"vocabulary":6,"volume":25.85,"operands":{"distinct":2,"total":3,"identifiers":["__stripped__"]},"operators":{"distinct":4,"total":7,"identifiers":["__stripped__"]}},"params":0,"sloc":{"logical":1,"physical":3},"errors":[],"lineEnd":1115,"lineStart":1113,"name":"<anonymous>","complexity":{"cyclomatic":2,"sloc":{"logical":1,"physical":3},"halstead":{"bugs":0.009,"difficulty":3,"effort":77.549,"length":10,"time":4.308,"vocabulary":6,"volume":25.85,"operands":{"distinct":2,"total":3,"identifiers":["__stripped__"]},"operators":{"distinct":4,"total":7,"identifiers":["__stripped__"]}}},"line":1113},{"cyclomatic":1,"cyclomaticDensity":50,"halstead":{"bugs":0.008,"difficulty":2.5,"effort":60,"length":8,"time":3.333,"vocabulary":8,"volume":24,"operands":{"distinct":3,"total":3,"identifiers":["__stripped__"]},"operators":{"distinct":5,"total":5,"identifiers":["__stripped__"]}},"params":0,"sloc":{"logical":2,"physical":5},"errors":[],"lineEnd":1134,"lineStart":1130,"name":"<anonymous>","complexity":{"cyclomatic":1,"sloc":{"logical":2,"physical":5},"halstead":{"bugs":0.008,"difficulty":2.5,"effort":60,"length":8,"time":3.333,"vocabulary":8,"volume":24,"operands":{"distinct":3,"total":3,"identifiers":["__stripped__"]},"operators":{"distinct":5,"total":5,"identifiers":["__stripped__"]}}},"line":1130},{"cyclomatic":3,"cyclomaticDensity":42.857,"halstead":{"bugs":0.065,"difficulty":7.269,"effort":1426.332,"length":44,"time":79.241,"vocabulary":22,"volume":196.215,"operands":{"distinct":13,"total":21,"identifiers":["__stripped__"]},"operators":{"distinct":9,"total":23,"identifiers":["__stripped__"]}},"params":1,"sloc":{"logical":7,"physical":11},"errors":[],"lineEnd":1211,"lineStart":1201,"name":"<anonymous>","complexity":{"cyclomatic":3,"sloc":{"logical":7,"physical":11},"halstead":{"bugs":0.065,"difficulty":7.269,"effort":1426.332,"length":44,"time":79.241,"vocabulary":22,"volume":196.215,"operands":{"distinct":13,"total":21,"identifiers":["__stripped__"]},"operators":{"distinct":9,"total":23,"identifiers":["__stripped__"]}}},"line":1201},{"cyclomatic":2,"cyclomaticDensity":200,"halstead":{"bugs":0.017,"difficulty":4,"effort":199.316,"length":15,"time":11.073,"vocabulary":10,"volume":49.829,"operands":{"distinct":5,"total":8,"identifiers":["__stripped__"]},"operators":{"distinct":5,"total":7,"identifiers":["__stripped__"]}},"params":2,"sloc":{"logical":1,"physical":20},"errors":[],"lineEnd":1236,"lineStart":1217,"name":"<anonymous>","complexity":{"cyclomatic":2,"sloc":{"logical":1,"physical":20},"halstead":{"bugs":0.017,"difficulty":4,"effort":199.316,"length":15,"time":11.073,"vocabulary":10,"volume":49.829,"operands":{"distinct":5,"total":8,"identifiers":["__stripped__"]},"operators":{"distinct":5,"total":7,"identifiers":["__stripped__"]}}},"line":1217},{"cyclomatic":1,"cyclomaticDensity":7.143,"halstead":{"bugs":0.112,"difficulty":5.371,"effort":1800.786,"length":63,"time":100.044,"vocabulary":40,"volume":335.281,"operands":{"distinct":31,"total":37,"identifiers":["__stripped__"]},"operators":{"distinct":9,"total":26,"identifiers":["__stripped__"]}},"params":2,"sloc":{"logical":14,"physical":18},"errors":[],"lineEnd":1235,"lineStart":1218,"name":"<anonymous>","complexity":{"cyclomatic":1,"sloc":{"logical":14,"physical":18},"halstead":{"bugs":0.112,"difficulty":5.371,"effort":1800.786,"length":63,"time":100.044,"vocabulary":40,"volume":335.281,"operands":{"distinct":31,"total":37,"identifiers":["__stripped__"]},"operators":{"distinct":9,"total":26,"identifiers":["__stripped__"]}}},"line":1218},{"cyclomatic":1,"cyclomaticDensity":100,"halstead":{"bugs":0.003,"difficulty":1,"effort":8,"length":4,"time":0.444,"vocabulary":4,"volume":8,"operands":{"distinct":2,"total":2,"identifiers":["__stripped__"]},"operators":{"distinct":2,"total":2,"identifiers":["__stripped__"]}},"params":0,"sloc":{"logical":1,"physical":7},"errors":[],"lineEnd":1322,"lineStart":1316,"name":"<anonymous>","complexity":{"cyclomatic":1,"sloc":{"logical":1,"physical":7},"halstead":{"bugs":0.003,"difficulty":1,"effort":8,"length":4,"time":0.444,"vocabulary":4,"volume":8,"operands":{"distinct":2,"total":2,"identifiers":["__stripped__"]},"operators":{"distinct":2,"total":2,"identifiers":["__stripped__"]}}},"line":1316},{"cyclomatic":1,"cyclomaticDensity":50,"halstead":{"bugs":0.008,"difficulty":2,"effort":48,"length":8,"time":2.667,"vocabulary":8,"volume":24,"operands":{"distinct":4,"total":4,"identifiers":["__stripped__"]},"operators":{"distinct":4,"total":4,"identifiers":["__stripped__"]}},"params":0,"sloc":{"logical":2,"physical":5},"errors":[],"lineEnd":1321,"lineStart":1317,"name":"<anonymous>","complexity":{"cyclomatic":1,"sloc":{"logical":2,"physical":5},"halstead":{"bugs":0.008,"difficulty":2,"effort":48,"length":8,"time":2.667,"vocabulary":8,"volume":24,"operands":{"distinct":4,"total":4,"identifiers":["__stripped__"]},"operators":{"distinct":4,"total":4,"identifiers":["__stripped__"]}}},"line":1317},{"cyclomatic":9,"cyclomaticDensity":32.143,"halstead":{"bugs":0.331,"difficulty":17.306,"effort":17189.932,"length":176,"time":954.996,"vocabulary":50,"volume":993.319,"operands":{"distinct":36,"total":89,"identifiers":["__stripped__"]},"operators":{"distinct":14,"total":87,"identifiers":["__stripped__"]}},"params":0,"sloc":{"logical":28,"physical":47},"errors":[],"lineEnd":1385,"lineStart":1339,"name":"<anonymous>","complexity":{"cyclomatic":9,"sloc":{"logical":28,"physical":47},"halstead":{"bugs":0.331,"difficulty":17.306,"effort":17189.932,"length":176,"time":954.996,"vocabulary":50,"volume":993.319,"operands":{"distinct":36,"total":89,"identifiers":["__stripped__"]},"operators":{"distinct":14,"total":87,"identifiers":["__stripped__"]}}},"line":1339},{"cyclomatic":1,"cyclomaticDensity":16.667,"halstead":{"bugs":0.038,"difficulty":5.091,"effort":583.897,"length":27,"time":32.439,"vocabulary":19,"volume":114.694,"operands":{"distinct":11,"total":14,"identifiers":["__stripped__"]},"operators":{"distinct":8,"total":13,"identifiers":["__stripped__"]}},"params":2,"sloc":{"logical":6,"physical":47},"errors":[],"lineEnd":1436,"lineStart":1390,"name":"<anonymous>","complexity":{"cyclomatic":1,"sloc":{"logical":6,"physical":47},"halstead":{"bugs":0.038,"difficulty":5.091,"effort":583.897,"length":27,"time":32.439,"vocabulary":19,"volume":114.694,"operands":{"distinct":11,"total":14,"identifiers":["__stripped__"]},"operators":{"distinct":8,"total":13,"identifiers":["__stripped__"]}}},"line":1390},{"cyclomatic":7,"cyclomaticDensity":25,"halstead":{"bugs":0.326,"difficulty":16.4,"effort":16022.136,"length":174,"time":890.119,"vocabulary":49,"volume":976.96,"operands":{"distinct":35,"total":82,"identifiers":["__stripped__"]},"operators":{"distinct":14,"total":92,"identifiers":["__stripped__"]}},"params":1,"sloc":{"logical":28,"physical":38},"errors":[],"lineEnd":1435,"lineStart":1398,"name":"<anonymous>","complexity":{"cyclomatic":7,"sloc":{"logical":28,"physical":38},"halstead":{"bugs":0.326,"difficulty":16.4,"effort":16022.136,"length":174,"time":890.119,"vocabulary":49,"volume":976.96,"operands":{"distinct":35,"total":82,"identifiers":["__stripped__"]},"operators":{"distinct":14,"total":92,"identifiers":["__stripped__"]}}},"line":1398}],"methodAverage":{"cyclomatic":3.16,"cyclomaticDensity":61.839,"halstead":{"bugs":0.097,"difficulty":7.464,"effort":4586.144,"length":56.2,"time":254.786,"vocabulary":21.76,"volume":289.84,"operands":{"distinct":14.04,"total":27.88},"operators":{"distinct":7.72,"total":28.32}},"params":0.76,"sloc":{"logical":9.44,"physical":19.36}},"module":"page/airport-transportation/airport-transportation.js","aggregate":{"complexity":{"cyclomatic":238,"cyclomaticDensity":24.612,"halstead":{"bugs":17.386,"difficulty":126.757,"effort":6611476.052,"length":5854,"time":367304.225,"vocabulary":481,"volume":52158.514,"operands":{"distinct":441,"total":2795,"identifiers":["__stripped__"]},"operators":{"distinct":40,"total":3059,"identifiers":["__stripped__"]}},"params":19,"sloc":{"logical":967,"physical":1438}}},"functions":[{"cyclomatic":1,"cyclomaticDensity":100,"halstead":{"bugs":0.014,"difficulty":2,"effort":82.418,"length":13,"time":4.579,"vocabulary":9,"volume":41.209,"operands":{"distinct":6,"total":8,"identifiers":["__stripped__"]},"operators":{"distinct":3,"total":5,"identifiers":["__stripped__"]}},"params":1,"sloc":{"logical":1,"physical":3},"errors":[],"lineEnd":272,"lineStart":270,"name":"<anonymous>","complexity":{"cyclomatic":1,"sloc":{"logical":1,"physical":3},"halstead":{"bugs":0.014,"difficulty":2,"effort":82.418,"length":13,"time":4.579,"vocabulary":9,"volume":41.209,"operands":{"distinct":6,"total":8,"identifiers":["__stripped__"]},"operators":{"distinct":3,"total":5,"identifiers":["__stripped__"]}}},"line":270},{"cyclomatic":1,"cyclomaticDensity":50,"halstead":{"bugs":0.008,"difficulty":2,"effort":48,"length":8,"time":2.667,"vocabulary":8,"volume":24,"operands":{"distinct":4,"total":4,"identifiers":["__stripped__"]},"operators":{"distinct":4,"total":4,"identifiers":["__stripped__"]}},"params":0,"sloc":{"logical":2,"physical":5},"errors":[],"lineEnd":434,"lineStart":430,"name":"<anonymous>","complexity":{"cyclomatic":1,"sloc":{"logical":2,"physical":5},"halstead":{"bugs":0.008,"difficulty":2,"effort":48,"length":8,"time":2.667,"vocabulary":8,"volume":24,"operands":{"distinct":4,"total":4,"identifiers":["__stripped__"]},"operators":{"distinct":4,"total":4,"identifiers":["__stripped__"]}}},"line":430},{"cyclomatic":1,"cyclomaticDensity":33.333,"halstead":{"bugs":0.018,"difficulty":4.8,"effort":265.684,"length":16,"time":14.76,"vocabulary":11,"volume":55.351,"operands":{"distinct":5,"total":8,"identifiers":["__stripped__"]},"operators":{"distinct":6,"total":8,"identifiers":["__stripped__"]}},"params":1,"sloc":{"logical":3,"physical":7},"errors":[],"lineEnd":469,"lineStart":463,"name":"<anonymous>","complexity":{"cyclomatic":1,"sloc":{"logical":3,"physical":7},"halstead":{"bugs":0.018,"difficulty":4.8,"effort":265.684,"length":16,"time":14.76,"vocabulary":11,"volume":55.351,"operands":{"distinct":5,"total":8,"identifiers":["__stripped__"]},"operators":{"distinct":6,"total":8,"identifiers":["__stripped__"]}}},"line":463},{"cyclomatic":1,"cyclomaticDensity":100,"halstead":{"bugs":0.005,"difficulty":2.25,"effort":31.346,"length":6,"time":1.741,"vocabulary":5,"volume":13.932,"operands":{"distinct":2,"total":3,"identifiers":["__stripped__"]},"operators":{"distinct":3,"total":3,"identifiers":["__stripped__"]}},"params":1,"sloc":{"logical":1,"physical":3},"errors":[],"lineEnd":468,"lineStart":466,"name":"<anonymous>","complexity":{"cyclomatic":1,"sloc":{"logical":1,"physical":3},"halstead":{"bugs":0.005,"difficulty":2.25,"effort":31.346,"length":6,"time":1.741,"vocabulary":5,"volume":13.932,"operands":{"distinct":2,"total":3,"identifiers":["__stripped__"]},"operators":{"distinct":3,"total":3,"identifiers":["__stripped__"]}}},"line":466},{"cyclomatic":1,"cyclomaticDensity":50,"halstead":{"bugs":0.008,"difficulty":2,"effort":48,"length":8,"time":2.667,"vocabulary":8,"volume":24,"operands":{"distinct":4,"total":4,"identifiers":["__stripped__"]},"operators":{"distinct":4,"total":4,"identifiers":["__stripped__"]}},"params":0,"sloc":{"logical":2,"physical":5},"errors":[],"lineEnd":490,"lineStart":486,"name":"<anonymous>","complexity":{"cyclomatic":1,"sloc":{"logical":2,"physical":5},"halstead":{"bugs":0.008,"difficulty":2,"effort":48,"length":8,"time":2.667,"vocabulary":8,"volume":24,"operands":{"distinct":4,"total":4,"identifiers":["__stripped__"]},"operators":{"distinct":4,"total":4,"identifiers":["__stripped__"]}}},"line":486},{"cyclomatic":6,"cyclomaticDensity":23.077,"halstead":{"bugs":0.193,"difficulty":17.182,"effort":9964.952,"length":114,"time":553.608,"vocabulary":34,"volume":579.971,"operands":{"distinct":22,"total":63,"identifiers":["__stripped__"]},"operators":{"distinct":12,"total":51,"identifiers":["__stripped__"]}},"params":1,"sloc":{"logical":26,"physical":36},"errors":[],"lineEnd":573,"lineStart":538,"name":"<anonymous>","complexity":{"cyclomatic":6,"sloc":{"logical":26,"physical":36},"halstead":{"bugs":0.193,"difficulty":17.182,"effort":9964.952,"length":114,"time":553.608,"vocabulary":34,"volume":579.971,"operands":{"distinct":22,"total":63,"identifiers":["__stripped__"]},"operators":{"distinct":12,"total":51,"identifiers":["__stripped__"]}}},"line":538},{"cyclomatic":2,"cyclomaticDensity":100,"halstead":{"bugs":0.026,"difficulty":3,"effort":234.413,"length":20,"time":13.023,"vocabulary":15,"volume":78.138,"operands":{"distinct":9,"total":9,"identifiers":["__stripped__"]},"operators":{"distinct":6,"total":11,"identifiers":["__stripped__"]}},"params":0,"sloc":{"logical":2,"physical":10},"errors":[],"lineEnd":591,"lineStart":582,"name":"<anonymous>","complexity":{"cyclomatic":2,"sloc":{"logical":2,"physical":10},"halstead":{"bugs":0.026,"difficulty":3,"effort":234.413,"length":20,"time":13.023,"vocabulary":15,"volume":78.138,"operands":{"distinct":9,"total":9,"identifiers":["__stripped__"]},"operators":{"distinct":6,"total":11,"identifiers":["__stripped__"]}}},"line":582},{"cyclomatic":1,"cyclomaticDensity":50,"halstead":{"bugs":0.017,"difficulty":2.5,"effort":126.797,"length":16,"time":7.044,"vocabulary":9,"volume":50.719,"operands":{"distinct":6,"total":10,"identifiers":["__stripped__"]},"operators":{"distinct":3,"total":6,"identifiers":["__stripped__"]}},"params":1,"sloc":{"logical":2,"physical":6},"errors":[],"lineEnd":589,"lineStart":584,"name":"<anonymous>","complexity":{"cyclomatic":1,"sloc":{"logical":2,"physical":6},"halstead":{"bugs":0.017,"difficulty":2.5,"effort":126.797,"length":16,"time":7.044,"vocabulary":9,"volume":50.719,"operands":{"distinct":6,"total":10,"identifiers":["__stripped__"]},"operators":{"distinct":3,"total":6,"identifiers":["__stripped__"]}}},"line":584},{"cyclomatic":7,"cyclomaticDensity":35,"halstead":{"bugs":0.261,"difficulty":27,"effort":21110.923,"length":145,"time":1172.829,"vocabulary":42,"volume":781.886,"operands":{"distinct":24,"total":72,"identifiers":["__stripped__"]},"operators":{"distinct":18,"total":73,"identifiers":["__stripped__"]}},"params":1,"sloc":{"logical":20,"physical":46},"errors":[],"lineEnd":739,"lineStart":694,"name":"<anonymous>","complexity":{"cyclomatic":7,"sloc":{"logical":20,"physical":46},"halstead":{"bugs":0.261,"difficulty":27,"effort":21110.923,"length":145,"time":1172.829,"vocabulary":42,"volume":781.886,"operands":{"distinct":24,"total":72,"identifiers":["__stripped__"]},"operators":{"distinct":18,"total":73,"identifiers":["__stripped__"]}}},"line":694},{"cyclomatic":1,"cyclomaticDensity":7.143,"halstead":{"bugs":0.089,"difficulty":3.173,"effort":848.882,"length":54,"time":47.16,"vocabulary":31,"volume":267.527,"operands":{"distinct":26,"total":33,"identifiers":["__stripped__"]},"operators":{"distinct":5,"total":21,"identifiers":["__stripped__"]}},"params":2,"sloc":{"logical":14,"physical":19},"errors":[],"lineEnd":734,"lineStart":716,"name":"<anonymous>","complexity":{"cyclomatic":1,"sloc":{"logical":14,"physical":19},"halstead":{"bugs":0.089,"difficulty":3.173,"effort":848.882,"length":54,"time":47.16,"vocabulary":31,"volume":267.527,"operands":{"distinct":26,"total":33,"identifiers":["__stripped__"]},"operators":{"distinct":5,"total":21,"identifiers":["__stripped__"]}}},"line":716},{"cyclomatic":3,"cyclomaticDensity":100,"halstead":{"bugs":0.045,"difficulty":7,"effort":952,"length":34,"time":52.889,"vocabulary":16,"volume":136,"operands":{"distinct":9,"total":18,"identifiers":["__stripped__"]},"operators":{"distinct":7,"total":16,"identifiers":["__stripped__"]}},"params":1,"sloc":{"logical":3,"physical":6},"errors":[],"lineEnd":767,"lineStart":762,"name":"<anonymous>","complexity":{"cyclomatic":3,"sloc":{"logical":3,"physical":6},"halstead":{"bugs":0.045,"difficulty":7,"effort":952,"length":34,"time":52.889,"vocabulary":16,"volume":136,"operands":{"distinct":9,"total":18,"identifiers":["__stripped__"]},"operators":{"distinct":7,"total":16,"identifiers":["__stripped__"]}}},"line":762},{"cyclomatic":10,"cyclomaticDensity":58.824,"halstead":{"bugs":0.253,"difficulty":16.571,"effort":12575.411,"length":139,"time":698.634,"vocabulary":44,"volume":758.861,"operands":{"distinct":28,"total":58,"identifiers":["__stripped__"]},"operators":{"distinct":16,"total":81,"identifiers":["__stripped__"]}},"params":1,"sloc":{"logical":17,"physical":24},"errors":[],"lineEnd":798,"lineStart":775,"name":"<anonymous>","complexity":{"cyclomatic":10,"sloc":{"logical":17,"physical":24},"halstead":{"bugs":0.253,"difficulty":16.571,"effort":12575.411,"length":139,"time":698.634,"vocabulary":44,"volume":758.861,"operands":{"distinct":28,"total":58,"identifiers":["__stripped__"]},"operators":{"distinct":16,"total":81,"identifiers":["__stripped__"]}}},"line":775},{"cyclomatic":1,"cyclomaticDensity":50,"halstead":{"bugs":0.008,"difficulty":2.5,"effort":60,"length":8,"time":3.333,"vocabulary":8,"volume":24,"operands":{"distinct":3,"total":3,"identifiers":["__stripped__"]},"operators":{"distinct":5,"total":5,"identifiers":["__stripped__"]}},"params":0,"sloc":{"logical":2,"physical":5},"errors":[],"lineEnd":809,"lineStart":805,"name":"<anonymous>","complexity":{"cyclomatic":1,"sloc":{"logical":2,"physical":5},"halstead":{"bugs":0.008,"difficulty":2.5,"effort":60,"length":8,"time":3.333,"vocabulary":8,"volume":24,"operands":{"distinct":3,"total":3,"identifiers":["__stripped__"]},"operators":{"distinct":5,"total":5,"identifiers":["__stripped__"]}}},"line":805},{"cyclomatic":10,"cyclomaticDensity":26.316,"halstead":{"bugs":0.437,"difficulty":20.953,"effort":27476.932,"length":222,"time":1526.496,"vocabulary":60,"volume":1311.33,"operands":{"distinct":43,"total":106,"identifiers":["__stripped__"]},"operators":{"distinct":17,"total":116,"identifiers":["__stripped__"]}},"params":1,"sloc":{"logical":38,"physical":79},"errors":[],"lineEnd":1021,"lineStart":943,"name":"<anonymous>","complexity":{"cyclomatic":10,"sloc":{"logical":38,"physical":79},"halstead":{"bugs":0.437,"difficulty":20.953,"effort":27476.932,"length":222,"time":1526.496,"vocabulary":60,"volume":1311.33,"operands":{"distinct":43,"total":106,"identifiers":["__stripped__"]},"operators":{"distinct":17,"total":116,"identifiers":["__stripped__"]}}},"line":943},{"cyclomatic":5,"cyclomaticDensity":38.462,"halstead":{"bugs":0.117,"difficulty":9.722,"effort":3411.887,"length":73,"time":189.549,"vocabulary":28,"volume":350.937,"operands":{"distinct":18,"total":35,"identifiers":["__stripped__"]},"operators":{"distinct":10,"total":38,"identifiers":["__stripped__"]}},"params":0,"sloc":{"logical":13,"physical":29},"errors":[],"lineEnd":1009,"lineStart":981,"name":"<anonymous>","complexity":{"cyclomatic":5,"sloc":{"logical":13,"physical":29},"halstead":{"bugs":0.117,"difficulty":9.722,"effort":3411.887,"length":73,"time":189.549,"vocabulary":28,"volume":350.937,"operands":{"distinct":18,"total":35,"identifiers":["__stripped__"]},"operators":{"distinct":10,"total":38,"identifiers":["__stripped__"]}}},"line":981},{"cyclomatic":2,"cyclomaticDensity":200,"halstead":{"bugs":0.009,"difficulty":3,"effort":77.549,"length":10,"time":4.308,"vocabulary":6,"volume":25.85,"operands":{"distinct":2,"total":3,"identifiers":["__stripped__"]},"operators":{"distinct":4,"total":7,"identifiers":["__stripped__"]}},"params":0,"sloc":{"logical":1,"physical":3},"errors":[],"lineEnd":1115,"lineStart":1113,"name":"<anonymous>","complexity":{"cyclomatic":2,"sloc":{"logical":1,"physical":3},"halstead":{"bugs":0.009,"difficulty":3,"effort":77.549,"length":10,"time":4.308,"vocabulary":6,"volume":25.85,"operands":{"distinct":2,"total":3,"identifiers":["__stripped__"]},"operators":{"distinct":4,"total":7,"identifiers":["__stripped__"]}}},"line":1113},{"cyclomatic":1,"cyclomaticDensity":50,"halstead":{"bugs":0.008,"difficulty":2.5,"effort":60,"length":8,"time":3.333,"vocabulary":8,"volume":24,"operands":{"distinct":3,"total":3,"identifiers":["__stripped__"]},"operators":{"distinct":5,"total":5,"identifiers":["__stripped__"]}},"params":0,"sloc":{"logical":2,"physical":5},"errors":[],"lineEnd":1134,"lineStart":1130,"name":"<anonymous>","complexity":{"cyclomatic":1,"sloc":{"logical":2,"physical":5},"halstead":{"bugs":0.008,"difficulty":2.5,"effort":60,"length":8,"time":3.333,"vocabulary":8,"volume":24,"operands":{"distinct":3,"total":3,"identifiers":["__stripped__"]},"operators":{"distinct":5,"total":5,"identifiers":["__stripped__"]}}},"line":1130},{"cyclomatic":3,"cyclomaticDensity":42.857,"halstead":{"bugs":0.065,"difficulty":7.269,"effort":1426.332,"length":44,"time":79.241,"vocabulary":22,"volume":196.215,"operands":{"distinct":13,"total":21,"identifiers":["__stripped__"]},"operators":{"distinct":9,"total":23,"identifiers":["__stripped__"]}},"params":1,"sloc":{"logical":7,"physical":11},"errors":[],"lineEnd":1211,"lineStart":1201,"name":"<anonymous>","complexity":{"cyclomatic":3,"sloc":{"logical":7,"physical":11},"halstead":{"bugs":0.065,"difficulty":7.269,"effort":1426.332,"length":44,"time":79.241,"vocabulary":22,"volume":196.215,"operands":{"distinct":13,"total":21,"identifiers":["__stripped__"]},"operators":{"distinct":9,"total":23,"identifiers":["__stripped__"]}}},"line":1201},{"cyclomatic":2,"cyclomaticDensity":200,"halstead":{"bugs":0.017,"difficulty":4,"effort":199.316,"length":15,"time":11.073,"vocabulary":10,"volume":49.829,"operands":{"distinct":5,"total":8,"identifiers":["__stripped__"]},"operators":{"distinct":5,"total":7,"identifiers":["__stripped__"]}},"params":2,"sloc":{"logical":1,"physical":20},"errors":[],"lineEnd":1236,"lineStart":1217,"name":"<anonymous>","complexity":{"cyclomatic":2,"sloc":{"logical":1,"physical":20},"halstead":{"bugs":0.017,"difficulty":4,"effort":199.316,"length":15,"time":11.073,"vocabulary":10,"volume":49.829,"operands":{"distinct":5,"total":8,"identifiers":["__stripped__"]},"operators":{"distinct":5,"total":7,"identifiers":["__stripped__"]}}},"line":1217},{"cyclomatic":1,"cyclomaticDensity":7.143,"halstead":{"bugs":0.112,"difficulty":5.371,"effort":1800.786,"length":63,"time":100.044,"vocabulary":40,"volume":335.281,"operands":{"distinct":31,"total":37,"identifiers":["__stripped__"]},"operators":{"distinct":9,"total":26,"identifiers":["__stripped__"]}},"params":2,"sloc":{"logical":14,"physical":18},"errors":[],"lineEnd":1235,"lineStart":1218,"name":"<anonymous>","complexity":{"cyclomatic":1,"sloc":{"logical":14,"physical":18},"halstead":{"bugs":0.112,"difficulty":5.371,"effort":1800.786,"length":63,"time":100.044,"vocabulary":40,"volume":335.281,"operands":{"distinct":31,"total":37,"identifiers":["__stripped__"]},"operators":{"distinct":9,"total":26,"identifiers":["__stripped__"]}}},"line":1218},{"cyclomatic":1,"cyclomaticDensity":100,"halstead":{"bugs":0.003,"difficulty":1,"effort":8,"length":4,"time":0.444,"vocabulary":4,"volume":8,"operands":{"distinct":2,"total":2,"identifiers":["__stripped__"]},"operators":{"distinct":2,"total":2,"identifiers":["__stripped__"]}},"params":0,"sloc":{"logical":1,"physical":7},"errors":[],"lineEnd":1322,"lineStart":1316,"name":"<anonymous>","complexity":{"cyclomatic":1,"sloc":{"logical":1,"physical":7},"halstead":{"bugs":0.003,"difficulty":1,"effort":8,"length":4,"time":0.444,"vocabulary":4,"volume":8,"operands":{"distinct":2,"total":2,"identifiers":["__stripped__"]},"operators":{"distinct":2,"total":2,"identifiers":["__stripped__"]}}},"line":1316},{"cyclomatic":1,"cyclomaticDensity":50,"halstead":{"bugs":0.008,"difficulty":2,"effort":48,"length":8,"time":2.667,"vocabulary":8,"volume":24,"operands":{"distinct":4,"total":4,"identifiers":["__stripped__"]},"operators":{"distinct":4,"total":4,"identifiers":["__stripped__"]}},"params":0,"sloc":{"logical":2,"physical":5},"errors":[],"lineEnd":1321,"lineStart":1317,"name":"<anonymous>","complexity":{"cyclomatic":1,"sloc":{"logical":2,"physical":5},"halstead":{"bugs":0.008,"difficulty":2,"effort":48,"length":8,"time":2.667,"vocabulary":8,"volume":24,"operands":{"distinct":4,"total":4,"identifiers":["__stripped__"]},"operators":{"distinct":4,"total":4,"identifiers":["__stripped__"]}}},"line":1317},{"cyclomatic":9,"cyclomaticDensity":32.143,"halstead":{"bugs":0.331,"difficulty":17.306,"effort":17189.932,"length":176,"time":954.996,"vocabulary":50,"volume":993.319,"operands":{"distinct":36,"total":89,"identifiers":["__stripped__"]},"operators":{"distinct":14,"total":87,"identifiers":["__stripped__"]}},"params":0,"sloc":{"logical":28,"physical":47},"errors":[],"lineEnd":1385,"lineStart":1339,"name":"<anonymous>","complexity":{"cyclomatic":9,"sloc":{"logical":28,"physical":47},"halstead":{"bugs":0.331,"difficulty":17.306,"effort":17189.932,"length":176,"time":954.996,"vocabulary":50,"volume":993.319,"operands":{"distinct":36,"total":89,"identifiers":["__stripped__"]},"operators":{"distinct":14,"total":87,"identifiers":["__stripped__"]}}},"line":1339},{"cyclomatic":1,"cyclomaticDensity":16.667,"halstead":{"bugs":0.038,"difficulty":5.091,"effort":583.897,"length":27,"time":32.439,"vocabulary":19,"volume":114.694,"operands":{"distinct":11,"total":14,"identifiers":["__stripped__"]},"operators":{"distinct":8,"total":13,"identifiers":["__stripped__"]}},"params":2,"sloc":{"logical":6,"physical":47},"errors":[],"lineEnd":1436,"lineStart":1390,"name":"<anonymous>","complexity":{"cyclomatic":1,"sloc":{"logical":6,"physical":47},"halstead":{"bugs":0.038,"difficulty":5.091,"effort":583.897,"length":27,"time":32.439,"vocabulary":19,"volume":114.694,"operands":{"distinct":11,"total":14,"identifiers":["__stripped__"]},"operators":{"distinct":8,"total":13,"identifiers":["__stripped__"]}}},"line":1390},{"cyclomatic":7,"cyclomaticDensity":25,"halstead":{"bugs":0.326,"difficulty":16.4,"effort":16022.136,"length":174,"time":890.119,"vocabulary":49,"volume":976.96,"operands":{"distinct":35,"total":82,"identifiers":["__stripped__"]},"operators":{"distinct":14,"total":92,"identifiers":["__stripped__"]}},"params":1,"sloc":{"logical":28,"physical":38},"errors":[],"lineEnd":1435,"lineStart":1398,"name":"<anonymous>","complexity":{"cyclomatic":7,"sloc":{"logical":28,"physical":38},"halstead":{"bugs":0.326,"difficulty":16.4,"effort":16022.136,"length":174,"time":890.119,"vocabulary":49,"volume":976.96,"operands":{"distinct":35,"total":82,"identifiers":["__stripped__"]},"operators":{"distinct":14,"total":92,"identifiers":["__stripped__"]}}},"line":1398}]},"eslint":{"messages":[{"severity":"error","line":10,"column":83,"message":"Missing semicolon.","fix":{"range":[690,690],"text":";"}},{"severity":"error","line":108,"column":9,"message":"Missing semicolon.","fix":{"range":[3646,3646],"text":";"}},{"severity":"error","line":112,"column":9,"message":"Missing semicolon.","fix":{"range":[3718,3718],"text":";"}},{"severity":"error","line":118,"column":34,"message":"Strings must use singlequote.","fix":{"range":[3880,3914],"text":"'single-search_addressInfoDetails'"}},{"severity":"error","line":121,"column":34,"message":"Strings must use singlequote.","fix":{"range":[4039,4075],"text":"'terminal-search_airportInfoDetails'"}},{"severity":"error","line":123,"column":54,"message":"Strings must use singlequote.","fix":{"range":[4229,4250],"text":"'enter-flight-number'"}},{"severity":"error","line":137,"column":9,"message":"Missing semicolon.","fix":{"range":[4657,4657],"text":";"}},{"severity":"error","line":139,"column":62,"message":"Missing semicolon.","fix":{"range":[4766,4766],"text":";"}},{"severity":"error","line":140,"column":40,"message":"Missing semicolon.","fix":{"range":[4807,4807],"text":";"}},{"severity":"error","line":141,"column":45,"message":"Missing semicolon.","fix":{"range":[4853,4853],"text":";"}},{"severity":"error","line":143,"column":42,"message":"Missing semicolon.","fix":{"range":[4915,4915],"text":";"}},{"severity":"error","line":152,"column":11,"message":"Missing semicolon.","fix":{"range":[5344,5344],"text":";"}},{"severity":"error","line":153,"column":42,"message":"Missing semicolon.","fix":{"range":[5387,5387],"text":";"}},{"severity":"error","line":156,"column":50,"message":"Missing semicolon.","fix":{"range":[5459,5459],"text":";"}},{"severity":"error","line":164,"column":9,"message":"Missing semicolon.","fix":{"range":[5750,5750],"text":";"}},{"severity":"error","line":169,"column":35,"message":"Missing semicolon.","fix":{"range":[5877,5877],"text":";"}},{"severity":"error","line":172,"column":52,"message":"Strings must use singlequote.","fix":{"range":[5952,5980],"text":"'airport-transportation-tab'"}},{"severity":"error","line":194,"column":44,"message":"Missing semicolon.","fix":{"range":[6778,6778],"text":";"}},{"severity":"error","line":195,"column":49,"message":"Missing semicolon.","fix":{"range":[6828,6828],"text":";"}},{"severity":"error","line":199,"column":31,"message":"Missing semicolon.","fix":{"range":[7019,7019],"text":";"}},{"severity":"error","line":202,"column":83,"message":"Missing semicolon.","fix":{"range":[7124,7124],"text":";"}},{"severity":"error","line":208,"column":7,"message":"Missing semicolon.","fix":{"range":[7202,7202],"text":";"}},{"severity":"error","line":224,"column":9,"message":"Missing semicolon.","fix":{"range":[7691,7691],"text":";"}},{"severity":"error","line":225,"column":63,"message":"Missing semicolon.","fix":{"range":[7755,7755],"text":";"}},{"severity":"error","line":226,"column":63,"message":"Missing semicolon.","fix":{"range":[7819,7819],"text":";"}},{"severity":"error","line":227,"column":65,"message":"Missing semicolon.","fix":{"range":[7885,7885],"text":";"}},{"severity":"error","line":228,"column":34,"message":"Missing semicolon.","fix":{"range":[7920,7920],"text":";"}},{"severity":"error","line":234,"column":11,"message":"Missing semicolon.","fix":{"range":[8058,8058],"text":";"}},{"severity":"error","line":244,"column":7,"message":"Missing semicolon.","fix":{"range":[8332,8332],"text":";"}},{"severity":"error","line":248,"column":54,"message":"Strings must use singlequote.","fix":{"range":[8473,8494],"text":"'enter-flight-number'"}},{"severity":"error","line":252,"column":9,"message":"Strings must use singlequote.","fix":{"range":[8644,8649],"text":"'lat'"}},{"severity":"error","line":253,"column":9,"message":"Strings must use singlequote.","fix":{"range":[8664,8669],"text":"'lon'"}},{"severity":"error","line":254,"column":9,"message":"Strings must use singlequote.","fix":{"range":[8684,8690],"text":"'name'"}},{"severity":"error","line":255,"column":8,"message":"Missing semicolon.","fix":{"range":[8703,8703],"text":";"}},{"severity":"error","line":259,"column":34,"message":"Missing semicolon.","fix":{"range":[8765,8765],"text":";"}},{"severity":"error","line":260,"column":46,"message":"Missing semicolon.","fix":{"range":[8822,8822],"text":";"}},{"severity":"error","line":261,"column":32,"message":"Missing semicolon.","fix":{"range":[8867,8867],"text":";"}},{"severity":"error","line":266,"column":101,"message":"Missing semicolon.","fix":{"range":[9065,9065],"text":";"}},{"severity":"error","line":267,"column":99,"message":"Missing semicolon.","fix":{"range":[9165,9165],"text":";"}},{"severity":"error","line":278,"column":57,"message":"Missing semicolon.","fix":{"range":[9586,9586],"text":";"}},{"severity":"error","line":281,"column":11,"message":"Missing semicolon.","fix":{"range":[9654,9654],"text":";"}},{"severity":"error","line":284,"column":59,"message":"Missing semicolon.","fix":{"range":[9836,9836],"text":";"}},{"severity":"error","line":289,"column":13,"message":"Missing semicolon.","fix":{"range":[9926,9926],"text":";"}},{"severity":"error","line":290,"column":39,"message":"Missing semicolon.","fix":{"range":[9966,9966],"text":";"}},{"severity":"error","line":291,"column":123,"message":"Missing semicolon.","fix":{"range":[10090,10090],"text":";"}},{"severity":"error","line":292,"column":123,"message":"Missing semicolon.","fix":{"range":[10214,10214],"text":";"}},{"severity":"error","line":307,"column":13,"message":"Missing semicolon.","fix":{"range":[10729,10729],"text":";"}},{"severity":"error","line":309,"column":13,"message":"Strings must use singlequote.","fix":{"range":[10801,10806],"text":"'lat'"}},{"severity":"error","line":310,"column":13,"message":"Strings must use singlequote.","fix":{"range":[10831,10836],"text":"'lon'"}},{"severity":"error","line":311,"column":13,"message":"Strings must use singlequote.","fix":{"range":[10861,10867],"text":"'name'"}},{"severity":"error","line":312,"column":12,"message":"Missing semicolon.","fix":{"range":[10897,10897],"text":";"}},{"severity":"error","line":314,"column":44,"message":"Missing semicolon.","fix":{"range":[11013,11013],"text":";"}},{"severity":"error","line":320,"column":50,"message":"Missing semicolon.","fix":{"range":[11156,11156],"text":";"}},{"severity":"error","line":322,"column":33,"message":"Missing semicolon.","fix":{"range":[11232,11232],"text":";"}},{"severity":"error","line":324,"column":24,"message":"Missing semicolon.","fix":{"range":[11284,11284],"text":";"}},{"severity":"error","line":325,"column":24,"message":"Missing semicolon.","fix":{"range":[11309,11309],"text":";"}},{"severity":"error","line":327,"column":98,"message":"Missing semicolon.","fix":{"range":[11430,11430],"text":";"}},{"severity":"error","line":328,"column":98,"message":"Missing semicolon.","fix":{"range":[11529,11529],"text":";"}},{"severity":"error","line":345,"column":92,"message":"Strings must use singlequote.","fix":{"range":[12332,12334],"text":"''"}},{"severity":"error","line":358,"column":12,"message":"Missing semicolon.","fix":{"range":[12788,12788],"text":";"}},{"severity":"error","line":361,"column":11,"message":"Missing semicolon.","fix":{"range":[12897,12897],"text":";"}},{"severity":"error","line":363,"column":70,"message":"Missing semicolon.","fix":{"range":[13000,13000],"text":";"}},{"severity":"error","line":364,"column":66,"message":"Missing semicolon.","fix":{"range":[13067,13067],"text":";"}},{"severity":"error","line":365,"column":109,"message":"Missing semicolon.","fix":{"range":[13177,13177],"text":";"}},{"severity":"error","line":369,"column":26,"message":"Missing semicolon.","fix":{"range":[13240,13240],"text":";"}},{"severity":"error","line":370,"column":60,"message":"Missing semicolon.","fix":{"range":[13301,13301],"text":";"}},{"severity":"error","line":371,"column":58,"message":"Missing semicolon.","fix":{"range":[13360,13360],"text":";"}},{"severity":"error","line":379,"column":12,"message":"Missing semicolon.","fix":{"range":[13886,13886],"text":";"}},{"severity":"error","line":395,"column":10,"message":"Missing semicolon.","fix":{"range":[14435,14435],"text":";"}},{"severity":"error","line":399,"column":9,"message":"Missing semicolon.","fix":{"range":[14659,14659],"text":";"}},{"severity":"error","line":401,"column":9,"message":"Strings must use singlequote.","fix":{"range":[14733,14738],"text":"'lat'"}},{"severity":"error","line":402,"column":9,"message":"Strings must use singlequote.","fix":{"range":[14835,14840],"text":"'lon'"}},{"severity":"error","line":403,"column":9,"message":"Strings must use singlequote.","fix":{"range":[14937,14943],"text":"'name'"}},{"severity":"error","line":404,"column":8,"message":"Missing semicolon.","fix":{"range":[15041,15041],"text":";"}},{"severity":"error","line":406,"column":69,"message":"Missing semicolon.","fix":{"range":[15141,15141],"text":";"}},{"severity":"error","line":407,"column":65,"message":"Missing semicolon.","fix":{"range":[15207,15207],"text":";"}},{"severity":"error","line":408,"column":107,"message":"Missing semicolon.","fix":{"range":[15315,15315],"text":";"}},{"severity":"error","line":416,"column":99,"message":"Missing semicolon.","fix":{"range":[15616,15616],"text":";"}},{"severity":"error","line":417,"column":59,"message":"Missing semicolon.","fix":{"range":[15676,15676],"text":";"}},{"severity":"error","line":420,"column":17,"message":"Missing semicolon.","fix":{"range":[15816,15816],"text":";"}},{"severity":"error","line":428,"column":11,"message":"Missing semicolon.","fix":{"range":[15995,15995],"text":";"}},{"severity":"error","line":434,"column":16,"message":"Missing semicolon.","fix":{"range":[16137,16137],"text":";"}},{"severity":"error","line":435,"column":15,"message":"Missing semicolon.","fix":{"range":[16153,16153],"text":";"}},{"severity":"error","line":468,"column":9,"message":"Missing semicolon.","fix":{"range":[17289,17289],"text":";"}},{"severity":"error","line":490,"column":16,"message":"Missing semicolon.","fix":{"range":[18031,18031],"text":";"}},{"severity":"error","line":521,"column":26,"message":"Strings must use singlequote.","fix":{"range":[19034,19036],"text":"''"}},{"severity":"error","line":521,"column":28,"message":"Missing semicolon.","fix":{"range":[19036,19036],"text":";"}},{"severity":"error","line":523,"column":74,"message":"Strings must use singlequote.","fix":{"range":[19147,19149],"text":"''"}},{"severity":"error","line":523,"column":77,"message":"Missing semicolon.","fix":{"range":[19150,19150],"text":";"}},{"severity":"error","line":525,"column":48,"message":"Missing semicolon.","fix":{"range":[19219,19219],"text":";"}},{"severity":"error","line":527,"column":45,"message":"Missing semicolon.","fix":{"range":[19276,19276],"text":";"}},{"severity":"error","line":528,"column":34,"message":"Missing semicolon.","fix":{"range":[19311,19311],"text":";"}},{"severity":"error","line":531,"column":11,"message":"Missing semicolon.","fix":{"range":[19378,19378],"text":";"}},{"severity":"error","line":539,"column":27,"message":"Missing semicolon.","fix":{"range":[19579,19579],"text":";"}},{"severity":"error","line":541,"column":28,"message":"Missing semicolon.","fix":{"range":[19629,19629],"text":";"}},{"severity":"error","line":556,"column":12,"message":"Missing semicolon.","fix":{"range":[20024,20024],"text":";"}},{"severity":"error","line":563,"column":27,"message":"Missing semicolon.","fix":{"range":[20308,20308],"text":";"}},{"severity":"error","line":572,"column":11,"message":"Missing semicolon.","fix":{"range":[20710,20710],"text":";"}},{"severity":"error","line":573,"column":7,"message":"Missing semicolon.","fix":{"range":[20718,20718],"text":";"}},{"severity":"error","line":577,"column":5,"message":"Expected { after 'if' condition.","fix":{"range":[20856,20862],"text":"{return}"}},{"severity":"error","line":577,"column":67,"message":"Missing semicolon.","fix":{"range":[20862,20862],"text":";"}},{"severity":"error","line":589,"column":11,"message":"Missing semicolon.","fix":{"range":[21352,21352],"text":";"}},{"severity":"error","line":596,"column":5,"message":"Expected { after 'if' condition.","fix":{"range":[21482,21488],"text":"{return}"}},{"severity":"error","line":596,"column":67,"message":"Missing semicolon.","fix":{"range":[21488,21488],"text":";"}},{"severity":"error","line":619,"column":9,"message":"Strings must use singlequote.","fix":{"range":[22547,22552],"text":"'lat'"}},{"severity":"error","line":620,"column":9,"message":"Strings must use singlequote.","fix":{"range":[22596,22601],"text":"'lon'"}},{"severity":"error","line":621,"column":9,"message":"Strings must use singlequote.","fix":{"range":[22646,22652],"text":"'name'"}},{"severity":"error","line":622,"column":8,"message":"Missing semicolon.","fix":{"range":[22699,22699],"text":";"}},{"severity":"error","line":625,"column":11,"message":"Strings must use singlequote.","fix":{"range":[22802,22807],"text":"'lat'"}},{"severity":"error","line":626,"column":11,"message":"Strings must use singlequote.","fix":{"range":[22853,22858],"text":"'lon'"}},{"severity":"error","line":627,"column":11,"message":"Strings must use singlequote.","fix":{"range":[22905,22911],"text":"'name'"}},{"severity":"error","line":628,"column":10,"message":"Missing semicolon.","fix":{"range":[22960,22960],"text":";"}},{"severity":"error","line":634,"column":13,"message":"Strings must use singlequote.","fix":{"range":[23178,23183],"text":"'lat'"}},{"severity":"error","line":635,"column":13,"message":"Strings must use singlequote.","fix":{"range":[23231,23236],"text":"'lon'"}},{"severity":"error","line":636,"column":13,"message":"Strings must use singlequote.","fix":{"range":[23285,23291],"text":"'name'"}},{"severity":"error","line":638,"column":9,"message":"Missing semicolon.","fix":{"range":[23352,23352],"text":";"}},{"severity":"error","line":647,"column":13,"message":"Strings must use singlequote.","fix":{"range":[23823,23828],"text":"'lat'"}},{"severity":"error","line":648,"column":13,"message":"Strings must use singlequote.","fix":{"range":[23876,23881],"text":"'lon'"}},{"severity":"error","line":649,"column":13,"message":"Strings must use singlequote.","fix":{"range":[23930,23936],"text":"'name'"}},{"severity":"error","line":651,"column":9,"message":"Missing semicolon.","fix":{"range":[23997,23997],"text":";"}},{"severity":"error","line":659,"column":13,"message":"Strings must use singlequote.","fix":{"range":[24379,24384],"text":"'lat'"}},{"severity":"error","line":660,"column":13,"message":"Strings must use singlequote.","fix":{"range":[24432,24437],"text":"'lon'"}},{"severity":"error","line":661,"column":13,"message":"Strings must use singlequote.","fix":{"range":[24486,24492],"text":"'name'"}},{"severity":"error","line":663,"column":9,"message":"Missing semicolon.","fix":{"range":[24553,24553],"text":";"}},{"severity":"error","line":668,"column":5,"message":"Expected { after 'if' condition.","fix":{"range":[24691,24697],"text":"{return}"}},{"severity":"error","line":668,"column":67,"message":"Missing semicolon.","fix":{"range":[24697,24697],"text":";"}},{"severity":"error","line":689,"column":6,"message":"Missing semicolon.","fix":{"range":[25253,25253],"text":";"}},{"severity":"error","line":719,"column":21,"message":"Strings must use singlequote.","fix":{"range":[26441,26469],"text":"'/image/index/recopoint.png'"}},{"severity":"error","line":733,"column":11,"message":"Missing semicolon.","fix":{"range":[26856,26856],"text":";"}},{"severity":"error","line":734,"column":9,"message":"Missing semicolon.","fix":{"range":[26866,26866],"text":";"}},{"severity":"error","line":739,"column":7,"message":"Missing semicolon.","fix":{"range":[27053,27053],"text":";"}},{"severity":"error","line":746,"column":7,"message":"Missing semicolon.","fix":{"range":[27334,27334],"text":";"}},{"severity":"error","line":752,"column":36,"message":"Missing semicolon.","fix":{"range":[27598,27598],"text":";"}},{"severity":"error","line":760,"column":8,"message":"Missing semicolon.","fix":{"range":[27886,27886],"text":";"}},{"severity":"error","line":766,"column":10,"message":"Missing semicolon.","fix":{"range":[28125,28125],"text":";"}},{"severity":"error","line":767,"column":9,"message":"Missing semicolon.","fix":{"range":[28135,28135],"text":";"}},{"severity":"error","line":772,"column":5,"message":"Expected { after 'if' condition.","fix":{"range":[28298,28304],"text":"{return}"}},{"severity":"error","line":772,"column":83,"message":"Missing semicolon.","fix":{"range":[28304,28304],"text":";"}},{"severity":"error","line":774,"column":44,"message":"Missing semicolon.","fix":{"range":[28374,28374],"text":";"}},{"severity":"error","line":793,"column":13,"message":"Missing semicolon.","fix":{"range":[29218,29218],"text":";"}},{"severity":"error","line":795,"column":9,"message":"Expected { after 'if' condition.","fix":{"range":[29295,29301],"text":"{return}"}},{"severity":"error","line":795,"column":71,"message":"Missing semicolon.","fix":{"range":[29301,29301],"text":";"}},{"severity":"error","line":808,"column":11,"message":"Missing semicolon.","fix":{"range":[29693,29693],"text":";"}},{"severity":"error","line":809,"column":13,"message":"Missing semicolon.","fix":{"range":[29707,29707],"text":";"}},{"severity":"error","line":816,"column":7,"message":"Missing semicolon.","fix":{"range":[29848,29848],"text":";"}},{"severity":"error","line":822,"column":9,"message":"Missing semicolon.","fix":{"range":[29994,29994],"text":";"}},{"severity":"error","line":829,"column":9,"message":"Missing semicolon.","fix":{"range":[30149,30149],"text":";"}},{"severity":"error","line":835,"column":5,"message":"Missing semicolon.","fix":{"range":[30258,30258],"text":";"}},{"severity":"error","line":841,"column":9,"message":"Missing semicolon.","fix":{"range":[30457,30457],"text":";"}},{"severity":"error","line":842,"column":31,"message":"Missing semicolon.","fix":{"range":[30489,30489],"text":";"}},{"severity":"error","line":843,"column":40,"message":"Missing semicolon.","fix":{"range":[30530,30530],"text":";"}},{"severity":"error","line":846,"column":51,"message":"Missing semicolon.","fix":{"range":[30693,30693],"text":";"}},{"severity":"error","line":851,"column":35,"message":"Missing semicolon.","fix":{"range":[30959,30959],"text":";"}},{"severity":"error","line":854,"column":82,"message":"Missing semicolon.","fix":{"range":[31071,31071],"text":";"}},{"severity":"error","line":858,"column":13,"message":"Missing semicolon.","fix":{"range":[31178,31178],"text":";"}},{"severity":"error","line":865,"column":11,"message":"Missing semicolon.","fix":{"range":[31383,31383],"text":";"}},{"severity":"error","line":872,"column":9,"message":"Missing semicolon.","fix":{"range":[31583,31583],"text":";"}},{"severity":"error","line":873,"column":31,"message":"Missing semicolon.","fix":{"range":[31615,31615],"text":";"}},{"severity":"error","line":874,"column":40,"message":"Missing semicolon.","fix":{"range":[31656,31656],"text":";"}},{"severity":"error","line":880,"column":9,"message":"Missing semicolon.","fix":{"range":[31877,31877],"text":";"}},{"severity":"error","line":881,"column":31,"message":"Missing semicolon.","fix":{"range":[31909,31909],"text":";"}},{"severity":"error","line":882,"column":34,"message":"Missing semicolon.","fix":{"range":[31944,31944],"text":";"}},{"severity":"error","line":883,"column":54,"message":"Missing semicolon.","fix":{"range":[32006,32006],"text":";"}},{"severity":"error","line":894,"column":13,"message":"Missing semicolon.","fix":{"range":[32363,32363],"text":";"}},{"severity":"error","line":904,"column":13,"message":"Missing semicolon.","fix":{"range":[32742,32742],"text":";"}},{"severity":"error","line":909,"column":11,"message":"Missing semicolon.","fix":{"range":[32857,32857],"text":";"}},{"severity":"error","line":910,"column":34,"message":"Missing semicolon.","fix":{"range":[32892,32892],"text":";"}},{"severity":"error","line":911,"column":61,"message":"Missing semicolon.","fix":{"range":[32954,32954],"text":";"}},{"severity":"error","line":918,"column":11,"message":"Missing semicolon.","fix":{"range":[33304,33304],"text":";"}},{"severity":"error","line":921,"column":96,"message":"Missing semicolon.","fix":{"range":[33469,33469],"text":";"}},{"severity":"error","line":929,"column":13,"message":"Missing semicolon.","fix":{"range":[33676,33676],"text":";"}},{"severity":"error","line":942,"column":23,"message":"Missing semicolon.","fix":{"range":[34114,34114],"text":";"}},{"severity":"error","line":944,"column":23,"message":"Missing semicolon.","fix":{"range":[34186,34186],"text":";"}},{"severity":"error","line":946,"column":48,"message":"Missing semicolon.","fix":{"range":[34264,34264],"text":";"}},{"severity":"error","line":949,"column":47,"message":"Missing semicolon.","fix":{"range":[34420,34420],"text":";"}},{"severity":"error","line":950,"column":44,"message":"Missing semicolon.","fix":{"range":[34465,34465],"text":";"}},{"severity":"error","line":955,"column":15,"message":"Missing semicolon.","fix":{"range":[34670,34670],"text":";"}},{"severity":"error","line":965,"column":13,"message":"Missing semicolon.","fix":{"range":[35131,35131],"text":";"}},{"severity":"error","line":967,"column":44,"message":"Missing semicolon.","fix":{"range":[35195,35195],"text":";"}},{"severity":"error","line":969,"column":98,"message":"Missing semicolon.","fix":{"range":[35321,35321],"text":";"}},{"severity":"error","line":975,"column":13,"message":"Missing semicolon.","fix":{"range":[35497,35497],"text":";"}},{"severity":"error","line":990,"column":60,"message":"Strings must use singlequote.","fix":{"range":[35987,36009],"text":"'flight-number-ground'"}},{"severity":"error","line":996,"column":15,"message":"Missing semicolon.","fix":{"range":[36270,36270],"text":";"}},{"severity":"error","line":1005,"column":42,"message":"Strings must use singlequote.","fix":{"range":[36537,36539],"text":"''"}},{"severity":"error","line":1006,"column":15,"message":"Missing semicolon.","fix":{"range":[36555,36555],"text":";"}},{"severity":"error","line":1007,"column":50,"message":"Missing semicolon.","fix":{"range":[36606,36606],"text":";"}},{"severity":"error","line":1009,"column":15,"message":"Missing semicolon.","fix":{"range":[36635,36635],"text":";"}},{"severity":"error","line":1018,"column":13,"message":"Missing semicolon.","fix":{"range":[36864,36864],"text":";"}},{"severity":"error","line":1021,"column":7,"message":"Missing semicolon.","fix":{"range":[36892,36892],"text":";"}},{"severity":"error","line":1025,"column":37,"message":"Missing semicolon.","fix":{"range":[37003,37003],"text":";"}},{"severity":"error","line":1026,"column":39,"message":"Missing semicolon.","fix":{"range":[37043,37043],"text":";"}},{"severity":"error","line":1028,"column":21,"message":"Missing semicolon.","fix":{"range":[37107,37107],"text":";"}},{"severity":"error","line":1030,"column":21,"message":"Missing semicolon.","fix":{"range":[37177,37177],"text":";"}},{"severity":"error","line":1032,"column":38,"message":"Strings must use singlequote.","fix":{"range":[37228,37239],"text":"'$1$2$3'"}},{"severity":"error","line":1033,"column":33,"message":"Missing semicolon.","fix":{"range":[37275,37275],"text":";"}},{"severity":"error","line":1035,"column":35,"message":"Missing semicolon.","fix":{"range":[37339,37339],"text":";"}},{"severity":"error","line":1038,"column":27,"message":"Missing semicolon.","fix":{"range":[37383,37383],"text":";"}},{"severity":"error","line":1046,"column":14,"message":"Strings must use singlequote.","fix":{"range":[37681,37684],"text":"'-'"}},{"severity":"error","line":1046,"column":20,"message":"Strings must use singlequote.","fix":{"range":[37687,37690],"text":"'-'"}},{"severity":"error","line":1052,"column":9,"message":"Missing semicolon.","fix":{"range":[37883,37883],"text":";"}},{"severity":"error","line":1057,"column":11,"message":"Missing semicolon.","fix":{"range":[38087,38087],"text":";"}},{"severity":"error","line":1063,"column":7,"message":"Missing semicolon.","fix":{"range":[38190,38190],"text":";"}},{"severity":"error","line":1064,"column":42,"message":"Missing semicolon.","fix":{"range":[38233,38233],"text":";"}},{"severity":"error","line":1068,"column":46,"message":"Missing semicolon.","fix":{"range":[38405,38405],"text":";"}},{"severity":"error","line":1073,"column":9,"message":"Missing semicolon.","fix":{"range":[38541,38541],"text":";"}},{"severity":"error","line":1077,"column":9,"message":"Missing semicolon.","fix":{"range":[38615,38615],"text":";"}},{"severity":"error","line":1085,"column":7,"message":"Missing semicolon.","fix":{"range":[38820,38820],"text":";"}},{"severity":"error","line":1088,"column":5,"message":"Expected { after 'if' condition.","fix":{"range":[38937,38943],"text":"{return}"}},{"severity":"error","line":1088,"column":83,"message":"Missing semicolon.","fix":{"range":[38943,38943],"text":";"}},{"severity":"error","line":1094,"column":46,"message":"Missing semicolon.","fix":{"range":[39206,39206],"text":";"}},{"severity":"error","line":1099,"column":23,"message":"Strings must use singlequote.","fix":{"range":[39391,39419],"text":"'/image/index/recopoint.png'"}},{"severity":"error","line":1108,"column":13,"message":"Missing semicolon.","fix":{"range":[39796,39796],"text":";"}},{"severity":"error","line":1115,"column":17,"message":"Missing semicolon.","fix":{"range":[40190,40190],"text":";"}},{"severity":"error","line":1118,"column":13,"message":"Missing semicolon.","fix":{"range":[40267,40267],"text":";"}},{"severity":"error","line":1122,"column":11,"message":"Missing semicolon.","fix":{"range":[40345,40345],"text":";"}},{"severity":"error","line":1125,"column":5,"message":"Expected { after 'if' condition.","fix":{"range":[40432,40438],"text":"{return}"}},{"severity":"error","line":1125,"column":49,"message":"Missing semicolon.","fix":{"range":[40438,40438],"text":";"}},{"severity":"error","line":1129,"column":7,"message":"Missing semicolon.","fix":{"range":[40534,40534],"text":";"}},{"severity":"error","line":1133,"column":9,"message":"Missing semicolon.","fix":{"range":[40619,40619],"text":";"}},{"severity":"error","line":1134,"column":11,"message":"Missing semicolon.","fix":{"range":[40631,40631],"text":";"}},{"severity":"error","line":1139,"column":9,"message":"Missing semicolon.","fix":{"range":[40805,40805],"text":";"}},{"severity":"error","line":1145,"column":9,"message":"Missing semicolon.","fix":{"range":[40973,40973],"text":";"}},{"severity":"error","line":1146,"column":83,"message":"Missing semicolon.","fix":{"range":[41057,41057],"text":";"}},{"severity":"error","line":1150,"column":5,"message":"Expected { after 'if' condition.","fix":{"range":[41154,41160],"text":"{return}"}},{"severity":"error","line":1150,"column":50,"message":"Missing semicolon.","fix":{"range":[41160,41160],"text":";"}},{"severity":"error","line":1154,"column":7,"message":"Missing semicolon.","fix":{"range":[41249,41249],"text":";"}},{"severity":"error","line":1159,"column":9,"message":"Missing semicolon.","fix":{"range":[41399,41399],"text":";"}},{"severity":"error","line":1161,"column":49,"message":"Missing semicolon.","fix":{"range":[41461,41461],"text":";"}},{"severity":"error","line":1167,"column":11,"message":"Missing semicolon.","fix":{"range":[41674,41674],"text":";"}},{"severity":"error","line":1168,"column":65,"message":"Missing semicolon.","fix":{"range":[41740,41740],"text":";"}},{"severity":"error","line":1169,"column":65,"message":"Missing semicolon.","fix":{"range":[41806,41806],"text":";"}},{"severity":"error","line":1170,"column":67,"message":"Missing semicolon.","fix":{"range":[41874,41874],"text":";"}},{"severity":"error","line":1171,"column":36,"message":"Missing semicolon.","fix":{"range":[41911,41911],"text":";"}},{"severity":"error","line":1172,"column":48,"message":"Missing semicolon.","fix":{"range":[41960,41960],"text":";"}},{"severity":"error","line":1182,"column":11,"message":"Missing semicolon.","fix":{"range":[42266,42266],"text":";"}},{"severity":"error","line":1183,"column":31,"message":"Missing semicolon.","fix":{"range":[42298,42298],"text":";"}},{"severity":"error","line":1211,"column":7,"message":"Missing semicolon.","fix":{"range":[43040,43040],"text":";"}},{"severity":"error","line":1233,"column":10,"message":"Missing semicolon.","fix":{"range":[43734,43734],"text":";"}},{"severity":"error","line":1235,"column":9,"message":"Missing semicolon.","fix":{"range":[43784,43784],"text":";"}},{"severity":"error","line":1236,"column":7,"message":"Missing semicolon.","fix":{"range":[43792,43792],"text":";"}},{"severity":"error","line":1246,"column":11,"message":"Missing semicolon.","fix":{"range":[44157,44157],"text":";"}},{"severity":"error","line":1266,"column":87,"message":"Missing semicolon.","fix":{"range":[44996,44996],"text":";"}},{"severity":"error","line":1280,"column":10,"message":"Missing semicolon.","fix":{"range":[45421,45421],"text":";"}},{"severity":"error","line":1285,"column":11,"message":"Duplicate key 'startMarkers[0].latitude'.","fix":{}},{"severity":"error","line":1286,"column":10,"message":"Missing semicolon.","fix":{"range":[45633,45633],"text":";"}},{"severity":"error","line":1287,"column":32,"message":"Missing semicolon.","fix":{"range":[45666,45666],"text":";"}},{"severity":"error","line":1297,"column":13,"message":"Missing semicolon.","fix":{"range":[45981,45981],"text":";"}},{"severity":"error","line":1303,"column":13,"message":"Missing semicolon.","fix":{"range":[46215,46215],"text":";"}},{"severity":"error","line":1309,"column":20,"message":"Missing semicolon.","fix":{"range":[46290,46290],"text":";"}},{"severity":"error","line":1313,"column":9,"message":"Missing semicolon.","fix":{"range":[46435,46435],"text":";"}},{"severity":"error","line":1320,"column":15,"message":"Missing semicolon.","fix":{"range":[46626,46626],"text":";"}},{"severity":"error","line":1321,"column":17,"message":"Missing semicolon.","fix":{"range":[46644,46644],"text":";"}},{"severity":"error","line":1325,"column":77,"message":"Missing semicolon.","fix":{"range":[46751,46751],"text":";"}},{"severity":"error","line":1328,"column":7,"message":"Missing semicolon.","fix":{"range":[46806,46806],"text":";"}},{"severity":"error","line":1337,"column":9,"message":"Missing semicolon.","fix":{"range":[47005,47005],"text":";"}},{"severity":"error","line":1347,"column":15,"message":"Missing semicolon.","fix":{"range":[47407,47407],"text":";"}},{"severity":"error","line":1349,"column":55,"message":"Missing semicolon.","fix":{"range":[47507,47507],"text":";"}},{"severity":"error","line":1351,"column":99,"message":"Missing semicolon.","fix":{"range":[47663,47663],"text":";"}},{"severity":"error","line":1353,"column":37,"message":"Missing semicolon.","fix":{"range":[47721,47721],"text":";"}},{"severity":"error","line":1356,"column":89,"message":"Missing semicolon.","fix":{"range":[47844,47844],"text":";"}},{"severity":"error","line":1365,"column":21,"message":"Missing semicolon.","fix":{"range":[48159,48159],"text":";"}},{"severity":"error","line":1369,"column":93,"message":"Missing semicolon.","fix":{"range":[48372,48372],"text":";"}},{"severity":"error","line":1376,"column":31,"message":"Strings must use singlequote.","fix":{"range":[48568,48573],"text":"'LBS'"}},{"severity":"error","line":1377,"column":21,"message":"Missing semicolon.","fix":{"range":[48595,48595],"text":";"}},{"severity":"error","line":1382,"column":13,"message":"Missing semicolon.","fix":{"range":[48691,48691],"text":";"}},{"severity":"error","line":1385,"column":14,"message":"Missing semicolon.","fix":{"range":[48719,48719],"text":";"}},{"severity":"error","line":1404,"column":15,"message":"Missing semicolon.","fix":{"range":[49266,49266],"text":";"}},{"severity":"error","line":1418,"column":15,"message":"Missing semicolon.","fix":{"range":[49819,49819],"text":";"}},{"severity":"error","line":1424,"column":15,"message":"Missing semicolon.","fix":{"range":[50010,50010],"text":";"}},{"severity":"error","line":1425,"column":63,"message":"Missing semicolon.","fix":{"range":[50086,50086],"text":";"}},{"severity":"error","line":1429,"column":37,"message":"Missing semicolon.","fix":{"range":[50208,50208],"text":";"}},{"severity":"error","line":1431,"column":62,"message":"Missing semicolon.","fix":{"range":[50329,50329],"text":";"}},{"severity":"error","line":1435,"column":9,"message":"Missing semicolon.","fix":{"range":[50452,50452],"text":";"}},{"severity":"error","line":1436,"column":7,"message":"Missing semicolon.","fix":{"range":[50460,50460],"text":";"}},{"severity":"error","line":1438,"column":3,"message":"Missing semicolon.","fix":{"range":[50470,50470],"text":";"}}]}}